function implementation through 4 cross 1 mux/design.sv
// Code your design here
module  four_cross_1mux(input [1:0] s, input [3:0] d, output y);
  assign y= ~s[0]&~s[1]&d[0] | s[0]&~s[1]&d[1] | ~s[0] &s[1]&d[2] | s[0]& s[1]&d[3];
endmodule



module function_using_mux(
    input A, B, C, D,
    output F
);

wire [3:0] in;

assign in[0] = ~A;
assign in[1] = A | B;
assign in[2] = 1'b0;
assign in[3] = 1'b1;

four_cross_1mux mux(
    .s({C,D}),
    .d(in),
    .y(F)
);

endmodule

function implementation through 4 cross 1 mux/testbench.sv
// Code your testbench here
// or browse Examples
module testbench;

    reg A, B, C, D;
    wire F;

    function_using_mux dut (
        .A(A),
        .B(B),
        .C(C),
        .D(D),
        .F(F)
    );

    integer i;

    initial begin
        $monitor("Time=%0t A=%b B=%b C=%b D=%b F=%b",
                  $time, A, B, C, D, F);

        for (i = 0; i < 16; i = i + 1) begin
            {A, B, C, D} = i;
            #10;
        end

        $finish;
    end

    initial begin
        $dumpfile("dump.vcd");
        $dumpvars(0, testbench);
    end

endmodule

function implementation through 4 cross 1 mux/simulation/dump.vcd
$date
	Sat Jul 18 11:02:17 2026
$end
$version
	Icarus Verilog
$end
$timescale
	1s
$end
$scope module testbench $end
$var wire 1 ! F $end
$var reg 1 " A $end
$var reg 1 # B $end
$var reg 1 $ C $end
$var reg 1 % D $end
$var integer 32 & i [31:0] $end
$scope module dut $end
$var wire 1 " A $end
$var wire 1 # B $end
$var wire 1 $ C $end
$var wire 1 % D $end
$var wire 4 ' in [3:0] $end
$var wire 1 ! F $end
$scope module mux $end
$var wire 4 ( d [3:0] $end
$var wire 2 ) s [1:0] $end
$var wire 1 ! y $end
$upscope $end
$upscope $end
$upscope $end
$enddefinitions $end
$comment Show the parameter values. $end
$dumpall
$end
#0
$dumpvars
b0 )
b1001 (
b1001 '
b0 &
0%
0$
0#
0"
1!
$end
#10
0!
b1 )
1%
b1 &
#20
1$
b10 )
0%
b10 &
#30
1!
b11 )
1%
b11 &
#40
1!
b1011 '
b1011 (
1#
0$
b0 )
0%
b100 &
#50
b1 )
1%
b101 &
#60
0!
1$
b10 )
0%
b110 &
#70
1!
b11 )
1%
b111 &
#80
0!
b1010 '
b1010 (
1"
0#
0$
b0 )
0%
b1000 &
#90
1!
b1 )
1%
b1001 &
#100
0!
1$
b10 )
0%
b1010 &
#110
1!
b11 )
1%
b1011 &
#120
0!
1#
0$
b0 )
0%
b1100 &
#130
1!
b1 )
1%
b1101 &
#140
0!
1$
b10 )
0%
b1110 &
#150
1!
b11 )
1%
b1111 &
#160
b10000 &
