full adder using half adder/design.sv
// Code your design here
module half_adder(input x, y, output [1:0]s);
  assign s[0] = x ^ y;
  assign s[1] = x&y;
endmodule



module full_adder(input x, y, cin, output [1:0]sum);
  wire [1:0]p;
  half_adder one(.x(x), .y(y), .s(p));
  
  wire [1:0] q;
  
  half_adder two(.x(p[0]), .y(cin), .s(q));
  
  assign sum[0]=q[0];
  assign sum[1] = p[1]|q[1];
endmodule

full adder using half adder/testbench.sv
// Code your testbench here
// or browse Examples
module testbench();
  
  reg [2:0] a;
  wire [1:0] s;
  full_adder dut(.x(a[2]), .y(a[1]), .cin(a[0]), .sum(s));
  
  reg clk;
  reg rst;
  
  initial begin
    clk=0;
    rst=1;
    #20
    rst=0;
  end
  
  always begin
    #10
    clk=~clk;
  end
  
  
  reg[2:0] i;
  
  always@(posedge clk or posedge rst) begin
    if(rst) begin
      i<=0;
      a<=0;
    end
    else begin
      a<=i;
      if(i==7) begin
        #10
        $finish;
      end
      else begin
        i<=i+1;
      end
      
    end
    
  end
  
  initial begin
    $monitor("t=%0t a=%b s=%b", $time, a, s);
  end
  
  initial begin
    $dumpfile("dump.vcd");
    $dumpvars(0, testbench);
  end
  
endmodule

full adder using half adder/dump.vcd
$date
	Mon Jul 20 10:47:58 2026
$end
$version
	Icarus Verilog
$end
$timescale
	1s
$end
$scope module testbench $end
$var wire 2 ! s [1:0] $end
$var reg 3 " a [2:0] $end
$var reg 1 # clk $end
$var reg 3 $ i [2:0] $end
$var reg 1 % rst $end
$scope module dut $end
$var wire 1 & cin $end
$var wire 1 ' x $end
$var wire 1 ( y $end
$var wire 2 ) sum [1:0] $end
$var wire 2 * q [1:0] $end
$var wire 2 + p [1:0] $end
$scope module one $end
$var wire 1 ' x $end
$var wire 1 ( y $end
$var wire 2 , s [1:0] $end
$upscope $end
$scope module two $end
$var wire 1 - x $end
$var wire 1 & y $end
$var wire 2 . s [1:0] $end
$upscope $end
$upscope $end
$upscope $end
$enddefinitions $end
$comment Show the parameter values. $end
$dumpall
$end
#0
$dumpvars
bx .
x-
bx ,
bx +
bx *
bx )
x(
x'
x&
1%
bx $
0#
bx "
bx !
$end
#10
b0 !
b0 )
0-
b0 +
b0 ,
b0 *
b0 .
0'
0(
0&
b0 "
b0 $
1#
#20
0#
0%
#30
b1 $
1#
#40
0#
#50
b1 !
b1 )
b1 *
b1 .
1&
b10 $
b1 "
1#
#60
0#
#70
1-
b1 !
b1 )
b1 +
b1 ,
b1 *
b1 .
1(
0&
b11 $
b10 "
1#
#80
0#
#90
b10 !
b10 )
b10 *
b10 .
1&
b100 $
b11 "
1#
#100
0#
#110
b1 !
b1 )
b1 *
b1 .
1'
0(
0&
b101 $
b100 "
1#
#120
0#
#130
b10 !
b10 )
b10 *
b10 .
1&
b110 $
b101 "
1#
#140
0#
#150
0-
b10 !
b10 )
b10 +
b10 ,
b0 *
b0 .
1(
0&
b111 $
b110 "
1#
#160
0#
#170
b11 !
b11 )
b1 *
b1 .
1&
b111 "
1#
