4 bit ripple carry adder/design.sv
// Code your design here
module half_adder(input x, y, output [1:0]s);
  assign s[0] = x ^ y;
  assign s[1] = x&y;
endmodule



module full_adder(input x, y, cin, output [1:0]sum);
  wire [1:0]p;
  half_adder one(.x(x), .y(y), .s(p));
  
  wire [1:0] q;
  
  half_adder two(.x(p[0]), .y(cin), .s(q));
  
  assign sum[0]=q[0];
  assign sum[1] = p[1]|q[1];
endmodule

  
  

module four_bit_adder(input [3:0]a,b, input cin, output [3:0]finalsum, output cout);
  wire [1:0] p;
  full_adder one(.x(a[0]), .y(b[0]), .cin(cin), .sum(p));
  assign finalsum[0]=p[0];
  
  
  wire [1:0] q;
  full_adder two(.x(a[1]), .y(b[1]), .cin(p[1]), .sum(q));
  assign finalsum[1]=q[0];
  
  wire [1:0] r;
  full_adder three(.x(a[2]), .y(b[2]), .cin(q[1]), .sum(r));
  assign finalsum[2]=r[0];
  
  wire [1:0] s;
  full_adder four(.x(a[3]), .y(b[3]), .cin(r[1]), .sum(s));
  assign finalsum[3]=s[0];
  
  assign cout=s[1];
  
endmodule

4 bit ripple carry adder/testbench.sv
// Code your testbench here
// or browse Examples
module testbench();
  reg [3:0] a;
  reg [3:0] b;
  reg cin;
  
  wire [3:0] sum;
  wire cout;
  
  
  four_bit_adder dut(.a(a), .b(b), .cin(cin), .finalsum(sum), .cout(cout));
  
  reg clk;
  reg rst;
  
  initial begin
    rst=1;
    clk=0;
    #20
    rst=0;
  end
  
  always begin
    #10
    clk=~clk;
  end
  
  integer i;
  initial begin
    i=0;
  end
  
  
  always@(posedge clk or posedge rst) begin
    if(rst) begin
      i<=0;
      {a,b,cin}<=0;
      
    end
    else begin
      {a,b,cin}<=i;
      if(i==511) begin
        #10;
        $finish;
      end
      else begin
        i<=i+1;
      end
        
    end
  end
  
  
  initial begin
    $monitor("time=%0t a=%b b=%b cin=%b cout=%b sum=%b",
              $time, a, b, cin, cout, sum);
  end


  initial begin
      $dumpfile("dump.vcd");
      $dumpvars(0, testbench);
  end
  
  
  
endmodule

4 bit ripple carry adder/dump.vcd
$date
	Mon Jul 20 11:41:46 2026
$end
$version
	Icarus Verilog
$end
$timescale
	1s
$end
$scope module testbench $end
$var wire 4 ! sum [3:0] $end
$var wire 1 " cout $end
$var reg 4 # a [3:0] $end
$var reg 4 $ b [3:0] $end
$var reg 1 % cin $end
$var reg 1 & clk $end
$var reg 1 ' rst $end
$var integer 32 ( i [31:0] $end
$scope module dut $end
$var wire 4 ) a [3:0] $end
$var wire 4 * b [3:0] $end
$var wire 1 % cin $end
$var wire 2 + s [1:0] $end
$var wire 2 , r [1:0] $end
$var wire 2 - q [1:0] $end
$var wire 2 . p [1:0] $end
$var wire 4 / finalsum [3:0] $end
$var wire 1 " cout $end
$scope module four $end
$var wire 1 0 cin $end
$var wire 1 1 x $end
$var wire 1 2 y $end
$var wire 2 3 sum [1:0] $end
$var wire 2 4 q [1:0] $end
$var wire 2 5 p [1:0] $end
$scope module one $end
$var wire 1 1 x $end
$var wire 1 2 y $end
$var wire 2 6 s [1:0] $end
$upscope $end
$scope module two $end
$var wire 1 7 x $end
$var wire 1 0 y $end
$var wire 2 8 s [1:0] $end
$upscope $end
$upscope $end
$scope module one $end
$var wire 1 % cin $end
$var wire 1 9 x $end
$var wire 1 : y $end
$var wire 2 ; sum [1:0] $end
$var wire 2 < q [1:0] $end
$var wire 2 = p [1:0] $end
$scope module one $end
$var wire 1 9 x $end
$var wire 1 : y $end
$var wire 2 > s [1:0] $end
$upscope $end
$scope module two $end
$var wire 1 ? x $end
$var wire 1 % y $end
$var wire 2 @ s [1:0] $end
$upscope $end
$upscope $end
$scope module three $end
$var wire 1 A cin $end
$var wire 1 B x $end
$var wire 1 C y $end
$var wire 2 D sum [1:0] $end
$var wire 2 E q [1:0] $end
$var wire 2 F p [1:0] $end
$scope module one $end
$var wire 1 B x $end
$var wire 1 C y $end
$var wire 2 G s [1:0] $end
$upscope $end
$scope module two $end
$var wire 1 H x $end
$var wire 1 A y $end
$var wire 2 I s [1:0] $end
$upscope $end
$upscope $end
$scope module two $end
$var wire 1 J cin $end
$var wire 1 K x $end
$var wire 1 L y $end
$var wire 2 M sum [1:0] $end
$var wire 2 N q [1:0] $end
$var wire 2 O p [1:0] $end
$scope module one $end
$var wire 1 K x $end
$var wire 1 L y $end
$var wire 2 P s [1:0] $end
$upscope $end
$scope module two $end
$var wire 1 Q x $end
$var wire 1 J y $end
$var wire 2 R s [1:0] $end
$upscope $end
$upscope $end
$upscope $end
$upscope $end
$enddefinitions $end
$comment Show the parameter values. $end
$dumpall
$end
#0
$dumpvars
bx R
xQ
bx P
bx O
bx N
bx M
xL
xK
xJ
bx I
xH
bx G
bx F
bx E
bx D
xC
xB
xA
bx @
x?
bx >
bx =
bx <
bx ;
x:
x9
bx 8
x7
bx 6
bx 5
bx 4
bx 3
x2
x1
x0
bx /
bx .
bx -
bx ,
bx +
bx *
bx )
b0 (
1'
0&
x%
bx $
bx #
x"
bx !
$end
#10
0A
00
0"
b0 !
b0 /
b0 -
b0 M
b0 ,
b0 D
b0 +
b0 3
0J
b0 .
b0 ;
b0 N
b0 R
b0 E
b0 I
b0 4
b0 8
0?
0Q
0H
07
b0 =
b0 >
b0 O
b0 P
b0 F
b0 G
b0 5
b0 6
09
0K
0B
01
0:
0L
0C
02
b0 <
b0 @
b0 #
b0 )
b0 $
b0 *
0%
1&
#20
0&
0'
#30
b1 (
1&
#40
0&
#50
b1 !
b1 /
b1 .
b1 ;
b1 <
b1 @
b10 (
1%
1&
#60
0&
#70
1?
b1 !
b1 /
b1 =
b1 >
b1 .
b1 ;
1:
b1 <
b1 @
b11 (
b1 $
b1 *
0%
1&
#80
0&
#90
b1 -
b1 M
b1 N
b1 R
1J
b10 !
b10 /
b10 .
b10 ;
b10 <
b10 @
b100 (
1%
1&
#100
0&
#110
0J
0?
1Q
b10 !
b10 /
b0 =
b0 >
b1 O
b1 P
b0 .
b0 ;
0:
1L
b0 <
b0 @
b101 (
b10 $
b10 *
0%
1&
#120
0&
#130
b11 !
b11 /
b1 .
b1 ;
b1 <
b1 @
b110 (
1%
1&
#140
0&
#150
1?
b11 !
b11 /
b1 =
b1 >
b1 .
b1 ;
1:
b1 <
b1 @
b111 (
b11 $
b11 *
0%
1&
#160
0&
#170
b1 ,
b1 D
b1 E
b1 I
1A
b10 -
b10 M
b10 N
b10 R
1J
b100 !
b100 /
b10 .
b10 ;
b10 <
b10 @
b1000 (
1%
1&
#180
0&
#190
b0 +
b0 3
b0 4
b0 8
0A
00
b0 -
b0 M
b1 ,
b1 D
b0 N
b0 R
b1 E
b1 I
0J
0?
0Q
1H
b100 !
b100 /
b0 =
b0 >
b0 O
b0 P
b1 F
b1 G
b0 .
b0 ;
0:
0L
1C
b0 <
b0 @
b1001 (
b100 $
b100 *
0%
1&
#200
0&
#210
b101 !
b101 /
b1 .
b1 ;
b1 <
b1 @
b1010 (
1%
1&
#220
0&
#230
1?
b101 !
b101 /
b1 =
b1 >
b1 .
b1 ;
1:
b1 <
b1 @
b1011 (
b101 $
b101 *
0%
1&
#240
0&
#250
b1 -
b1 M
b1 N
b1 R
1J
b110 !
b110 /
b10 .
b10 ;
b10 <
b10 @
b1100 (
1%
1&
#260
0&
#270
0J
0?
1Q
b110 !
b110 /
b0 =
b0 >
b1 O
b1 P
b0 .
b0 ;
0:
1L
b0 <
b0 @
b1101 (
b110 $
b110 *
0%
1&
#280
0&
#290
b111 !
b111 /
b1 .
b1 ;
b1 <
b1 @
b1110 (
1%
1&
#300
0&
#310
1?
b111 !
b111 /
b1 =
b1 >
b1 .
b1 ;
1:
b1 <
b1 @
b1111 (
b111 $
b111 *
0%
1&
#320
0&
#330
b1 +
b1 3
b1 4
b1 8
10
b10 ,
b10 D
b10 E
b10 I
1A
b10 -
b10 M
b10 N
b10 R
1J
b1000 !
b1000 /
b10 .
b10 ;
b10 <
b10 @
b10000 (
1%
1&
#340
0&
#350
0A
00
0"
b0 -
b0 M
b0 ,
b0 D
b1 +
b1 3
b0 N
b0 R
b0 E
b0 I
b1 4
b1 8
0J
0?
0Q
0H
17
b1000 !
b1000 /
b0 =
b0 >
b0 O
b0 P
b0 F
b0 G
b1 5
b1 6
b0 .
b0 ;
0:
0L
0C
12
b0 <
b0 @
b10001 (
b1000 $
b1000 *
0%
1&
#360
0&
#370
b1001 !
b1001 /
b1 .
b1 ;
b1 <
b1 @
b10010 (
1%
1&
#380
0&
#390
1?
b1001 !
b1001 /
b1 =
b1 >
b1 .
b1 ;
1:
b1 <
b1 @
b10011 (
b1001 $
b1001 *
0%
1&
#400
0&
#410
b1 -
b1 M
b1 N
b1 R
1J
b1010 !
b1010 /
b10 .
b10 ;
b10 <
b10 @
b10100 (
1%
1&
#420
0&
#430
0J
0?
1Q
b1010 !
b1010 /
b0 =
b0 >
b1 O
b1 P
b0 .
b0 ;
0:
1L
b0 <
b0 @
b10101 (
b1010 $
b1010 *
0%
1&
#440
0&
#450
b1011 !
b1011 /
b1 .
b1 ;
b1 <
b1 @
b10110 (
1%
1&
#460
0&
#470
1?
b1011 !
b1011 /
b1 =
b1 >
b1 .
b1 ;
1:
b1 <
b1 @
b10111 (
b1011 $
b1011 *
0%
1&
#480
0&
#490
b1 ,
b1 D
b1 E
b1 I
1A
b10 -
b10 M
b10 N
b10 R
1J
b1100 !
b1100 /
b10 .
b10 ;
b10 <
b10 @
b11000 (
1%
1&
#500
0&
#510
0"
b1 +
b1 3
b1 4
b1 8
0A
00
b0 -
b0 M
b1 ,
b1 D
b0 N
b0 R
b1 E
b1 I
0J
0?
0Q
1H
b1100 !
b1100 /
b0 =
b0 >
b0 O
b0 P
b1 F
b1 G
b0 .
b0 ;
0:
0L
1C
b0 <
b0 @
b11001 (
b1100 $
b1100 *
0%
1&
#520
0&
#530
b1101 !
b1101 /
b1 .
b1 ;
b1 <
b1 @
b11010 (
1%
1&
#540
0&
#550
1?
b1101 !
b1101 /
b1 =
b1 >
b1 .
b1 ;
1:
b1 <
b1 @
b11011 (
b1101 $
b1101 *
0%
1&
#560
0&
#570
b1 -
b1 M
b1 N
b1 R
1J
b1110 !
b1110 /
b10 .
b10 ;
b10 <
b10 @
b11100 (
1%
1&
#580
0&
#590
0J
0?
1Q
b1110 !
b1110 /
b0 =
b0 >
b1 O
b1 P
b0 .
b0 ;
0:
1L
b0 <
b0 @
b11101 (
b1110 $
b1110 *
0%
1&
#600
0&
#610
b1111 !
b1111 /
b1 .
b1 ;
b1 <
b1 @
b11110 (
1%
1&
#620
0&
#630
1?
b1111 !
b1111 /
b1 =
b1 >
b1 .
b1 ;
1:
b1 <
b1 @
b11111 (
b1111 $
b1111 *
0%
1&
#640
0&
#650
1"
b10 +
b10 3
b10 4
b10 8
10
b10 ,
b10 D
b10 E
b10 I
1A
b10 -
b10 M
b10 N
b10 R
1J
b0 !
b0 /
b10 .
b10 ;
b10 <
b10 @
b100000 (
1%
1&
#660
0&
#670
0A
00
0"
b0 -
b0 M
b0 ,
b0 D
b0 +
b0 3
b0 N
b0 R
b0 E
b0 I
b0 4
b0 8
0J
0Q
0H
07
b1 !
b1 /
b0 O
b0 P
b0 F
b0 G
b0 5
b0 6
b1 .
b1 ;
19
0:
0L
0C
02
b1 <
b1 @
b100001 (
b1 #
b1 )
b0 $
b0 *
0%
1&
#680
0&
#690
b1 -
b1 M
b1 N
b1 R
1J
b10 !
b10 /
b10 .
b10 ;
b10 <
b10 @
b100010 (
1%
1&
#700
0&
#710
b1 -
b1 M
b1 N
b1 R
1J
0?
b10 !
b10 /
b10 =
b10 >
b10 .
b10 ;
1:
b0 <
b0 @
b100011 (
b1 $
b1 *
0%
1&
#720
0&
#730
b11 !
b11 /
b11 .
b11 ;
b1 <
b1 @
b100100 (
1%
1&
#740
0&
#750
b0 ,
b0 D
b0 E
b0 I
0A
0J
b1 -
b1 M
b1 N
b1 R
1?
1Q
b11 !
b11 /
b1 =
b1 >
b1 O
b1 P
b1 .
b1 ;
0:
1L
b1 <
b1 @
b100101 (
b10 $
b10 *
0%
1&
#760
0&
#770
b1 ,
b1 D
b1 E
b1 I
1A
b10 -
b10 M
b10 N
b10 R
1J
b100 !
b100 /
b10 .
b10 ;
b10 <
b10 @
b100110 (
1%
1&
#780
0&
#790
b1 ,
b1 D
b1 E
b1 I
1A
b10 -
b10 M
b10 N
b10 R
1J
0?
b100 !
b100 /
b10 =
b10 >
b10 .
b10 ;
1:
b0 <
b0 @
b100111 (
b11 $
b11 *
0%
1&
#800
0&
#810
b101 !
b101 /
b11 .
b11 ;
b1 <
b1 @
b101000 (
1%
1&
#820
0&
#830
b0 +
b0 3
b0 4
b0 8
0A
00
0J
b0 -
b0 M
b1 ,
b1 D
b0 N
b0 R
b1 E
b1 I
1?
0Q
1H
b101 !
b101 /
b1 =
b1 >
b0 O
b0 P
b1 F
b1 G
b1 .
b1 ;
0:
0L
1C
b1 <
b1 @
b101001 (
b100 $
b100 *
0%
1&
#840
0&
#850
b1 -
b1 M
b1 N
b1 R
1J
b110 !
b110 /
b10 .
b10 ;
b10 <
b10 @
b101010 (
1%
1&
#860
0&
#870
b1 -
b1 M
b1 N
b1 R
1J
0?
b110 !
b110 /
b10 =
b10 >
b10 .
b10 ;
1:
b0 <
b0 @
b101011 (
b101 $
b101 *
0%
1&
#880
0&
#890
b111 !
b111 /
b11 .
b11 ;
b1 <
b1 @
b101100 (
1%
1&
#900
0&
#910
b0 +
b0 3
b0 4
b0 8
00
b1 ,
b1 D
b1 E
b1 I
0A
0J
b1 -
b1 M
b1 N
b1 R
1?
1Q
b111 !
b111 /
b1 =
b1 >
b1 O
b1 P
b1 .
b1 ;
0:
1L
b1 <
b1 @
b101101 (
b110 $
b110 *
0%
1&
#920
0&
#930
b1 +
b1 3
b1 4
b1 8
10
b10 ,
b10 D
b10 E
b10 I
1A
b10 -
b10 M
b10 N
b10 R
1J
b1000 !
b1000 /
b10 .
b10 ;
b10 <
b10 @
b101110 (
1%
1&
#940
0&
#950
b1 +
b1 3
b1 4
b1 8
10
b10 ,
b10 D
b10 E
b10 I
1A
b10 -
b10 M
b10 N
b10 R
1J
0?
b1000 !
b1000 /
b10 =
b10 >
b10 .
b10 ;
1:
b0 <
b0 @
b101111 (
b111 $
b111 *
0%
1&
#960
0&
#970
b1001 !
b1001 /
b11 .
b11 ;
b1 <
b1 @
b110000 (
1%
1&
#980
0&
#990
0A
00
0"
0J
b0 -
b0 M
b0 ,
b0 D
b1 +
b1 3
b0 N
b0 R
b0 E
b0 I
b1 4
b1 8
1?
0Q
0H
17
b1001 !
b1001 /
b1 =
b1 >
b0 O
b0 P
b0 F
b0 G
b1 5
b1 6
b1 .
b1 ;
0:
0L
0C
12
b1 <
b1 @
b110001 (
b1000 $
b1000 *
0%
1&
#1000
0&
#1010
b1 -
b1 M
b1 N
b1 R
1J
b1010 !
b1010 /
b10 .
b10 ;
b10 <
b10 @
b110010 (
1%
1&
#1020
0&
#1030
b1 -
b1 M
b1 N
b1 R
1J
0?
b1010 !
b1010 /
b10 =
b10 >
b10 .
b10 ;
1:
b0 <
b0 @
b110011 (
b1001 $
b1001 *
0%
1&
#1040
0&
#1050
b1011 !
b1011 /
b11 .
b11 ;
b1 <
b1 @
b110100 (
1%
1&
#1060
0&
#1070
b0 ,
b0 D
b0 E
b0 I
0A
0J
b1 -
b1 M
b1 N
b1 R
1?
1Q
b1011 !
b1011 /
b1 =
b1 >
b1 O
b1 P
b1 .
b1 ;
0:
1L
b1 <
b1 @
b110101 (
b1010 $
b1010 *
0%
1&
#1080
0&
#1090
b1 ,
b1 D
b1 E
b1 I
1A
b10 -
b10 M
b10 N
b10 R
1J
b1100 !
b1100 /
b10 .
b10 ;
b10 <
b10 @
b110110 (
1%
1&
#1100
0&
#1110
b1 ,
b1 D
b1 E
b1 I
1A
b10 -
b10 M
b10 N
b10 R
1J
0?
b1100 !
b1100 /
b10 =
b10 >
b10 .
b10 ;
1:
b0 <
b0 @
b110111 (
b1011 $
b1011 *
0%
1&
#1120
0&
#1130
b1101 !
b1101 /
b11 .
b11 ;
b1 <
b1 @
b111000 (
1%
1&
#1140
0&
#1150
0"
b1 +
b1 3
b1 4
b1 8
0A
00
0J
b0 -
b0 M
b1 ,
b1 D
b0 N
b0 R
b1 E
b1 I
1?
0Q
1H
b1101 !
b1101 /
b1 =
b1 >
b0 O
b0 P
b1 F
b1 G
b1 .
b1 ;
0:
0L
1C
b1 <
b1 @
b111001 (
b1100 $
b1100 *
0%
1&
#1160
0&
#1170
b1 -
b1 M
b1 N
b1 R
1J
b1110 !
b1110 /
b10 .
b10 ;
b10 <
b10 @
b111010 (
1%
1&
#1180
0&
#1190
b1 -
b1 M
b1 N
b1 R
1J
0?
b1110 !
b1110 /
b10 =
b10 >
b10 .
b10 ;
1:
b0 <
b0 @
b111011 (
b1101 $
b1101 *
0%
1&
#1200
0&
#1210
b1111 !
b1111 /
b11 .
b11 ;
b1 <
b1 @
b111100 (
1%
1&
#1220
0&
#1230
0"
b1 +
b1 3
b1 4
b1 8
00
b1 ,
b1 D
b1 E
b1 I
0A
0J
b1 -
b1 M
b1 N
b1 R
1?
1Q
b1111 !
b1111 /
b1 =
b1 >
b1 O
b1 P
b1 .
b1 ;
0:
1L
b1 <
b1 @
b111101 (
b1110 $
b1110 *
0%
1&
#1240
0&
#1250
1"
b10 +
b10 3
b10 4
b10 8
10
b10 ,
b10 D
b10 E
b10 I
1A
b10 -
b10 M
b10 N
b10 R
1J
b0 !
b0 /
b10 .
b10 ;
b10 <
b10 @
b111110 (
1%
1&
#1260
0&
#1270
1"
b10 +
b10 3
b10 4
b10 8
10
b10 ,
b10 D
b10 E
b10 I
1A
b10 -
b10 M
b10 N
b10 R
1J
0?
b0 !
b0 /
b10 =
b10 >
b10 .
b10 ;
1:
b0 <
b0 @
b111111 (
b1111 $
b1111 *
0%
1&
#1280
0&
#1290
b1 !
b1 /
b11 .
b11 ;
b1 <
b1 @
b1000000 (
1%
1&
#1300
0&
#1310
0A
b1 -
b1 M
00
0"
b1 N
b1 R
0J
b0 ,
b0 D
b0 +
b0 3
b0 E
b0 I
b0 4
b0 8
0H
07
b10 !
b10 /
b0 =
b0 >
b0 F
b0 G
b0 5
b0 6
b0 .
b0 ;
09
1K
0:
0L
0C
02
b0 <
b0 @
b1000001 (
b10 #
b10 )
b0 $
b0 *
0%
1&
#1320
0&
#1330
b11 !
b11 /
b1 .
b1 ;
b1 <
b1 @
b1000010 (
1%
1&
#1340
0&
#1350
1?
b11 !
b11 /
b1 =
b1 >
b1 .
b1 ;
1:
b1 <
b1 @
b1000011 (
b1 $
b1 *
0%
1&
#1360
0&
#1370
b1 ,
b1 D
b1 E
b1 I
1A
b10 -
b10 M
b10 N
b10 R
1J
b100 !
b100 /
b10 .
b10 ;
b10 <
b10 @
b1000100 (
1%
1&
#1380
0&
#1390
b0 N
b0 R
0J
0?
0Q
b100 !
b100 /
b0 =
b0 >
b10 O
b10 P
b0 .
b0 ;
0:
1L
b0 <
b0 @
b1000101 (
b10 $
b10 *
0%
1&
#1400
0&
#1410
b101 !
b101 /
b1 .
b1 ;
b1 <
b1 @
b1000110 (
1%
1&
#1420
0&
#1430
1?
b101 !
b101 /
b1 =
b1 >
b1 .
b1 ;
1:
b1 <
b1 @
b1000111 (
b11 $
b11 *
0%
1&
#1440
0&
#1450
b11 -
b11 M
b1 N
b1 R
1J
b110 !
b110 /
b10 .
b10 ;
b10 <
b10 @
b1001000 (
1%
1&
#1460
0&
#1470
b0 +
b0 3
b0 4
b0 8
00
0A
b1 ,
b1 D
b1 -
b1 M
b1 E
b1 I
0J
0?
1Q
1H
b110 !
b110 /
b0 =
b0 >
b1 O
b1 P
b1 F
b1 G
b0 .
b0 ;
0:
0L
1C
b0 <
b0 @
b1001001 (
b100 $
b100 *
0%
1&
#1480
0&
#1490
b111 !
b111 /
b1 .
b1 ;
b1 <
b1 @
b1001010 (
1%
1&
#1500
0&
#1510
1?
b111 !
b111 /
b1 =
b1 >
b1 .
b1 ;
1:
b1 <
b1 @
b1001011 (
b101 $
b101 *
0%
1&
#1520
0&
#1530
b1 +
b1 3
b1 4
b1 8
10
b10 ,
b10 D
b10 E
b10 I
1A
b10 -
b10 M
b10 N
b10 R
1J
b1000 !
b1000 /
b10 .
b10 ;
b10 <
b10 @
b1001100 (
1%
1&
#1540
0&
#1550
b0 N
b0 R
0J
0?
0Q
b1000 !
b1000 /
b0 =
b0 >
b10 O
b10 P
b0 .
b0 ;
0:
1L
b0 <
b0 @
b1001101 (
b110 $
b110 *
0%
1&
#1560
0&
#1570
b1001 !
b1001 /
b1 .
b1 ;
b1 <
b1 @
b1001110 (
1%
1&
#1580
0&
#1590
1?
b1001 !
b1001 /
b1 =
b1 >
b1 .
b1 ;
1:
b1 <
b1 @
b1001111 (
b111 $
b111 *
0%
1&
#1600
0&
#1610
b11 -
b11 M
b1 N
b1 R
1J
b1010 !
b1010 /
b10 .
b10 ;
b10 <
b10 @
b1010000 (
1%
1&
#1620
0&
#1630
00
0"
0A
b0 ,
b0 D
b1 +
b1 3
b1 -
b1 M
b0 E
b0 I
b1 4
b1 8
0J
0?
1Q
0H
17
b1010 !
b1010 /
b0 =
b0 >
b1 O
b1 P
b0 F
b0 G
b1 5
b1 6
b0 .
b0 ;
0:
0L
0C
12
b0 <
b0 @
b1010001 (
b1000 $
b1000 *
0%
1&
#1640
0&
#1650
b1011 !
b1011 /
b1 .
b1 ;
b1 <
b1 @
b1010010 (
1%
1&
#1660
0&
#1670
1?
b1011 !
b1011 /
b1 =
b1 >
b1 .
b1 ;
1:
b1 <
b1 @
b1010011 (
b1001 $
b1001 *
0%
1&
#1680
0&
#1690
b1 ,
b1 D
b1 E
b1 I
1A
b10 -
b10 M
b10 N
b10 R
1J
b1100 !
b1100 /
b10 .
b10 ;
b10 <
b10 @
b1010100 (
1%
1&
#1700
0&
#1710
b0 N
b0 R
0J
0?
0Q
b1100 !
b1100 /
b0 =
b0 >
b10 O
b10 P
b0 .
b0 ;
0:
1L
b0 <
b0 @
b1010101 (
b1010 $
b1010 *
0%
1&
#1720
0&
#1730
b1101 !
b1101 /
b1 .
b1 ;
b1 <
b1 @
b1010110 (
1%
1&
#1740
0&
#1750
1?
b1101 !
b1101 /
b1 =
b1 >
b1 .
b1 ;
1:
b1 <
b1 @
b1010111 (
b1011 $
b1011 *
0%
1&
#1760
0&
#1770
b11 -
b11 M
b1 N
b1 R
1J
b1110 !
b1110 /
b10 .
b10 ;
b10 <
b10 @
b1011000 (
1%
1&
#1780
0&
#1790
0"
b1 +
b1 3
b1 4
b1 8
00
0A
b1 ,
b1 D
b1 -
b1 M
b1 E
b1 I
0J
0?
1Q
1H
b1110 !
b1110 /
b0 =
b0 >
b1 O
b1 P
b1 F
b1 G
b0 .
b0 ;
0:
0L
1C
b0 <
b0 @
b1011001 (
b1100 $
b1100 *
0%
1&
#1800
0&
#1810
b1111 !
b1111 /
b1 .
b1 ;
b1 <
b1 @
b1011010 (
1%
1&
#1820
0&
#1830
1?
b1111 !
b1111 /
b1 =
b1 >
b1 .
b1 ;
1:
b1 <
b1 @
b1011011 (
b1101 $
b1101 *
0%
1&
#1840
0&
#1850
1"
b10 +
b10 3
b10 4
b10 8
10
b10 ,
b10 D
b10 E
b10 I
1A
b10 -
b10 M
b10 N
b10 R
1J
b0 !
b0 /
b10 .
b10 ;
b10 <
b10 @
b1011100 (
1%
1&
#1860
0&
#1870
b0 N
b0 R
0J
0?
0Q
b0 !
b0 /
b0 =
b0 >
b10 O
b10 P
b0 .
b0 ;
0:
1L
b0 <
b0 @
b1011101 (
b1110 $
b1110 *
0%
1&
#1880
0&
#1890
b1 !
b1 /
b1 .
b1 ;
b1 <
b1 @
b1011110 (
1%
1&
#1900
0&
#1910
1?
b1 !
b1 /
b1 =
b1 >
b1 .
b1 ;
1:
b1 <
b1 @
b1011111 (
b1111 $
b1111 *
0%
1&
#1920
0&
#1930
b11 -
b11 M
b1 N
b1 R
1J
b10 !
b10 /
b10 .
b10 ;
b10 <
b10 @
b1100000 (
1%
1&
#1940
0&
#1950
00
0"
0A
b0 ,
b0 D
b0 +
b0 3
b1 -
b1 M
b0 E
b0 I
b0 4
b0 8
0J
1Q
0H
07
b11 !
b11 /
b1 O
b1 P
b0 F
b0 G
b0 5
b0 6
b1 .
b1 ;
19
0:
0L
0C
02
b1 <
b1 @
b1100001 (
b11 #
b11 )
b0 $
b0 *
0%
1&
#1960
0&
#1970
b1 ,
b1 D
b1 E
b1 I
1A
b10 -
b10 M
b10 N
b10 R
1J
b100 !
b100 /
b10 .
b10 ;
b10 <
b10 @
b1100010 (
1%
1&
#1980
0&
#1990
b1 ,
b1 D
b1 E
b1 I
1A
b10 -
b10 M
b10 N
b10 R
1J
0?
b100 !
b100 /
b10 =
b10 >
b10 .
b10 ;
1:
b0 <
b0 @
b1100011 (
b1 $
b1 *
0%
1&
#2000
0&
#2010
b101 !
b101 /
b11 .
b11 ;
b1 <
b1 @
b1100100 (
1%
1&
#2020
0&
#2030
0J
b10 -
b10 M
b0 N
b0 R
1?
0Q
b101 !
b101 /
b1 =
b1 >
b10 O
b10 P
b1 .
b1 ;
0:
1L
b1 <
b1 @
b1100101 (
b10 $
b10 *
0%
1&
#2040
0&
#2050
b11 -
b11 M
b1 N
b1 R
1J
b110 !
b110 /
b10 .
b10 ;
b10 <
b10 @
b1100110 (
1%
1&
#2060
0&
#2070
b11 -
b11 M
b1 N
b1 R
1J
0?
b110 !
b110 /
b10 =
b10 >
b10 .
b10 ;
1:
b0 <
b0 @
b1100111 (
b11 $
b11 *
0%
1&
#2080
0&
#2090
b111 !
b111 /
b11 .
b11 ;
b1 <
b1 @
b1101000 (
1%
1&
#2100
0&
#2110
b0 +
b0 3
b0 4
b0 8
00
0J
0A
b1 ,
b1 D
b1 N
b1 R
b1 -
b1 M
b1 E
b1 I
1?
1Q
1H
b111 !
b111 /
b1 =
b1 >
b1 O
b1 P
b1 F
b1 G
b1 .
b1 ;
0:
0L
1C
b1 <
b1 @
b1101001 (
b100 $
b100 *
0%
1&
#2120
0&
#2130
b1 +
b1 3
b1 4
b1 8
10
b10 ,
b10 D
b10 E
b10 I
1A
b10 -
b10 M
b10 N
b10 R
1J
b1000 !
b1000 /
b10 .
b10 ;
b10 <
b10 @
b1101010 (
1%
1&
#2140
0&
#2150
b1 +
b1 3
b1 4
b1 8
10
b10 ,
b10 D
b10 E
b10 I
1A
b10 -
b10 M
b10 N
b10 R
1J
0?
b1000 !
b1000 /
b10 =
b10 >
b10 .
b10 ;
1:
b0 <
b0 @
b1101011 (
b101 $
b101 *
0%
1&
#2160
0&
#2170
b1001 !
b1001 /
b11 .
b11 ;
b1 <
b1 @
b1101100 (
1%
1&
#2180
0&
#2190
0J
b10 -
b10 M
b0 N
b0 R
1?
0Q
b1001 !
b1001 /
b1 =
b1 >
b10 O
b10 P
b1 .
b1 ;
0:
1L
b1 <
b1 @
b1101101 (
b110 $
b110 *
0%
1&
#2200
0&
#2210
b11 -
b11 M
b1 N
b1 R
1J
b1010 !
b1010 /
b10 .
b10 ;
b10 <
b10 @
b1101110 (
1%
1&
#2220
0&
#2230
b11 -
b11 M
b1 N
b1 R
1J
0?
b1010 !
b1010 /
b10 =
b10 >
b10 .
b10 ;
1:
b0 <
b0 @
b1101111 (
b111 $
b111 *
0%
1&
#2240
0&
#2250
b1011 !
b1011 /
b11 .
b11 ;
b1 <
b1 @
b1110000 (
1%
1&
#2260
0&
#2270
00
0"
0J
0A
b0 ,
b0 D
b1 +
b1 3
b1 N
b1 R
b1 -
b1 M
b0 E
b0 I
b1 4
b1 8
1?
1Q
0H
17
b1011 !
b1011 /
b1 =
b1 >
b1 O
b1 P
b0 F
b0 G
b1 5
b1 6
b1 .
b1 ;
0:
0L
0C
12
b1 <
b1 @
b1110001 (
b1000 $
b1000 *
0%
1&
#2280
0&
#2290
b1 ,
b1 D
b1 E
b1 I
1A
b10 -
b10 M
b10 N
b10 R
1J
b1100 !
b1100 /
b10 .
b10 ;
b10 <
b10 @
b1110010 (
1%
1&
#2300
0&
#2310
b1 ,
b1 D
b1 E
b1 I
1A
b10 -
b10 M
b10 N
b10 R
1J
0?
b1100 !
b1100 /
b10 =
b10 >
b10 .
b10 ;
1:
b0 <
b0 @
b1110011 (
b1001 $
b1001 *
0%
1&
#2320
0&
#2330
b1101 !
b1101 /
b11 .
b11 ;
b1 <
b1 @
b1110100 (
1%
1&
#2340
0&
#2350
0J
b10 -
b10 M
b0 N
b0 R
1?
0Q
b1101 !
b1101 /
b1 =
b1 >
b10 O
b10 P
b1 .
b1 ;
0:
1L
b1 <
b1 @
b1110101 (
b1010 $
b1010 *
0%
1&
#2360
0&
#2370
b11 -
b11 M
b1 N
b1 R
1J
b1110 !
b1110 /
b10 .
b10 ;
b10 <
b10 @
b1110110 (
1%
1&
#2380
0&
#2390
b11 -
b11 M
b1 N
b1 R
1J
0?
b1110 !
b1110 /
b10 =
b10 >
b10 .
b10 ;
1:
b0 <
b0 @
b1110111 (
b1011 $
b1011 *
0%
1&
#2400
0&
#2410
b1111 !
b1111 /
b11 .
b11 ;
b1 <
b1 @
b1111000 (
1%
1&
#2420
0&
#2430
0"
b1 +
b1 3
b1 4
b1 8
00
0J
0A
b1 ,
b1 D
b1 N
b1 R
b1 -
b1 M
b1 E
b1 I
1?
1Q
1H
b1111 !
b1111 /
b1 =
b1 >
b1 O
b1 P
b1 F
b1 G
b1 .
b1 ;
0:
0L
1C
b1 <
b1 @
b1111001 (
b1100 $
b1100 *
0%
1&
#2440
0&
