carry_look_ahead_adder/design.sv
// Code your design here
module carry_look_ahead_adder(input [3:0] a,b, input cin, output [3:0] sum, output carry);
  wire [3:0] P, G;
  
  wire c1, c2, c3, c4;
  
 
  assign P=a^b;
  assign G=a&b;
  assign c1 = G[0] | (P[0] & cin);

  assign c2 = G[1]
    | (P[1] & G[0])
    | (P[1] & P[0] & cin);

  assign c3 = G[2]
    | (P[2] & G[1])
    | (P[2] & P[1] & G[0])
    | (P[2] & P[1] & P[0] & cin);

  assign c4 = G[3]
    | (P[3] & G[2])
    | (P[3] & P[2] & G[1])
    | (P[3] & P[2] & P[1] & G[0])
    | (P[3] & P[2] & P[1] & P[0] & cin);
  
  assign sum[0]=P[0]^cin;
  assign sum[1]=P[1]^c1;
  assign sum[2]=P[2]^c2;
  assign sum[3]=P[3]^c3;
  
  assign carry = c4;
  
endmodule

carry_look_ahead_adder/testbench.sv
module tb;

    reg [3:0] a, b;
    reg cin;
    wire [3:0] sum;
    wire carry;

    carry_look_ahead_adder dut (
        .a(a),
        .b(b),
        .cin(cin),
        .sum(sum),
        .carry(carry)
    );

    integer i, j, k;

    initial begin
        for (k = 0; k < 2; k = k + 1) begin
            cin = k;
            for (i = 0; i < 16; i = i + 1) begin
                for (j = 0; j < 16; j = j + 1) begin
                    a = i;
                    b = j;
                    #10;

                    if ({carry, sum} !== (a + b + cin))
                        $display("ERROR: a=%0d b=%0d cin=%0d Expected=%0d Got=%0d",
                                 a, b, cin, a + b + cin, {carry, sum});
                end
            end
        end

        $display("All test cases completed.");
        $finish;
    end

   
    initial begin
        $monitor("Time=%0t | a=%d b=%d cin=%b | sum=%d carry=%b",
                 $time, a, b, cin, sum, carry);
    end

    
    initial begin
        $dumpfile("cla.vcd");
        $dumpvars(0, tb);
    end

endmodule

carry_look_ahead_adder/cla.vcd
$date
	Mon Jul 20 18:18:51 2026
$end
$version
	Icarus Verilog
$end
$timescale
	1s
$end
$scope module tb $end
$var wire 4 ! sum [3:0] $end
$var wire 1 " carry $end
$var reg 4 # a [3:0] $end
$var reg 4 $ b [3:0] $end
$var reg 1 % cin $end
$var integer 32 & i [31:0] $end
$var integer 32 ' j [31:0] $end
$var integer 32 ( k [31:0] $end
$scope module dut $end
$var wire 4 ) G [3:0] $end
$var wire 4 * P [3:0] $end
$var wire 4 + a [3:0] $end
$var wire 4 , b [3:0] $end
$var wire 1 - c1 $end
$var wire 1 . c2 $end
$var wire 1 / c3 $end
$var wire 1 0 c4 $end
$var wire 1 " carry $end
$var wire 1 % cin $end
$var wire 4 1 sum [3:0] $end
$upscope $end
$upscope $end
$enddefinitions $end
$comment Show the parameter values. $end
$dumpall
$end
#0
$dumpvars
b0 1
00
0/
0.
0-
b0 ,
b0 +
b0 *
b0 )
b0 (
b0 '
b0 &
0%
b0 $
b0 #
0"
b0 !
$end
#10
b1 !
b1 1
b1 *
b1 $
b1 ,
b1 '
#20
b10 !
b10 1
b10 *
b10 $
b10 ,
b10 '
#30
b11 !
b11 1
b11 *
b11 $
b11 ,
b11 '
#40
b100 !
b100 1
b100 *
b100 $
b100 ,
b100 '
#50
b101 !
b101 1
b101 *
b101 $
b101 ,
b101 '
#60
b110 !
b110 1
b110 *
b110 $
b110 ,
b110 '
#70
b111 !
b111 1
b111 *
b111 $
b111 ,
b111 '
#80
b1000 !
b1000 1
b1000 *
b1000 $
b1000 ,
b1000 '
#90
b1001 !
b1001 1
b1001 *
b1001 $
b1001 ,
b1001 '
#100
b1010 !
b1010 1
b1010 *
b1010 $
b1010 ,
b1010 '
#110
b1011 !
b1011 1
b1011 *
b1011 $
b1011 ,
b1011 '
#120
b1100 !
b1100 1
b1100 *
b1100 $
b1100 ,
b1100 '
#130
b1101 !
b1101 1
b1101 *
b1101 $
b1101 ,
b1101 '
#140
b1110 !
b1110 1
b1110 *
b1110 $
b1110 ,
b1110 '
#150
b1111 !
b1111 1
b1111 *
b1111 $
b1111 ,
b1111 '
#160
b1 !
b1 1
b1 *
b0 $
b0 ,
b1 #
b1 +
b1 &
b0 '
#170
b10 !
b10 1
1-
b0 *
b1 )
b1 $
b1 ,
b1 '
#180
b11 !
b11 1
0-
b11 *
b0 )
b10 $
b10 ,
b10 '
#190
1.
b100 !
b100 1
1-
b10 *
b1 )
b11 $
b11 ,
b11 '
#200
0.
b101 !
b101 1
0-
b101 *
b0 )
b100 $
b100 ,
b100 '
#210
b110 !
b110 1
1-
b100 *
b1 )
b101 $
b101 ,
b101 '
#220
b111 !
b111 1
0-
b111 *
b0 )
b110 $
b110 ,
b110 '
#230
1.
1/
b1000 !
b1000 1
1-
b110 *
b1 )
b111 $
b111 ,
b111 '
#240
0.
0/
b1001 !
b1001 1
0-
b1001 *
b0 )
b1000 $
b1000 ,
b1000 '
#250
b1010 !
b1010 1
1-
b1000 *
b1 )
b1001 $
b1001 ,
b1001 '
#260
b1011 !
b1011 1
0-
b1011 *
b0 )
b1010 $
b1010 ,
b1010 '
#270
1.
b1100 !
b1100 1
1-
b1010 *
b1 )
b1011 $
b1011 ,
b1011 '
#280
0.
b1101 !
b1101 1
0-
b1101 *
b0 )
b1100 $
b1100 ,
b1100 '
#290
b1110 !
b1110 1
1-
b1100 *
b1 )
b1101 $
b1101 ,
b1101 '
#300
b1111 !
b1111 1
0-
b1111 *
b0 )
b1110 $
b1110 ,
b1110 '
#310
1.
1/
1"
10
b0 !
b0 1
1-
b1110 *
b1 )
b1111 $
b1111 ,
b1111 '
#320
0.
0/
0"
00
b10 !
b10 1
0-
b10 *
b0 )
b0 $
b0 ,
b10 #
b10 +
b10 &
b0 '
#330
b11 !
b11 1
b11 *
b1 $
b1 ,
b1 '
#340
1.
b100 !
b100 1
b0 *
b10 )
b10 $
b10 ,
b10 '
#350
b101 !
b101 1
b1 *
b11 $
b11 ,
b11 '
#360
0.
b110 !
b110 1
b110 *
b0 )
b100 $
b100 ,
b100 '
#370
b111 !
b111 1
b111 *
b101 $
b101 ,
b101 '
#380
1/
1.
b1000 !
b1000 1
b100 *
b10 )
b110 $
b110 ,
b110 '
#390
b1001 !
b1001 1
b101 *
b111 $
b111 ,
b111 '
#400
0/
0.
b1010 !
b1010 1
b1010 *
b0 )
b1000 $
b1000 ,
b1000 '
#410
b1011 !
b1011 1
b1011 *
b1001 $
b1001 ,
b1001 '
#420
1.
b1100 !
b1100 1
b1000 *
b10 )
b1010 $
b1010 ,
b1010 '
#430
b1101 !
b1101 1
b1001 *
b1011 $
b1011 ,
b1011 '
#440
0.
b1110 !
b1110 1
b1110 *
b0 )
b1100 $
b1100 ,
b1100 '
#450
b1111 !
b1111 1
b1111 *
b1101 $
b1101 ,
b1101 '
#460
1/
1"
10
1.
b0 !
b0 1
b1100 *
b10 )
b1110 $
b1110 ,
b1110 '
#470
b1 !
b1 1
b1101 *
b1111 $
b1111 ,
b1111 '
#480
0/
0"
00
0.
b11 !
b11 1
b11 *
b0 )
b0 $
b0 ,
b11 #
b11 +
b11 &
b0 '
#490
1.
b100 !
b100 1
1-
b10 *
b1 )
b1 $
b1 ,
b1 '
#500
b101 !
b101 1
0-
b1 *
b10 )
b10 $
b10 ,
b10 '
#510
b110 !
b110 1
1-
b0 *
b11 )
b11 $
b11 ,
b11 '
#520
0.
b111 !
b111 1
0-
b111 *
b0 )
b100 $
b100 ,
b100 '
#530
1.
1/
b1000 !
b1000 1
1-
b110 *
b1 )
b101 $
b101 ,
b101 '
#540
1/
b1001 !
b1001 1
0-
b101 *
b10 )
b110 $
b110 ,
b110 '
#550
b1010 !
b1010 1
1-
b100 *
b11 )
b111 $
b111 ,
b111 '
#560
0/
0.
b1011 !
b1011 1
0-
b1011 *
b0 )
b1000 $
b1000 ,
b1000 '
#570
1.
b1100 !
b1100 1
1-
b1010 *
b1 )
b1001 $
b1001 ,
b1001 '
#580
b1101 !
b1101 1
0-
b1001 *
b10 )
b1010 $
b1010 ,
b1010 '
#590
b1110 !
b1110 1
1-
b1000 *
b11 )
b1011 $
b1011 ,
b1011 '
#600
0.
b1111 !
b1111 1
0-
b1111 *
b0 )
b1100 $
b1100 ,
b1100 '
#610
1.
1/
1"
10
b0 !
b0 1
1-
b1110 *
b1 )
b1101 $
b1101 ,
b1101 '
#620
1/
1"
10
b1 !
b1 1
0-
b1101 *
b10 )
b1110 $
b1110 ,
b1110 '
#630
b10 !
b10 1
1-
b1100 *
b11 )
b1111 $
b1111 ,
b1111 '
#640
0/
0"
00
0.
b100 !
b100 1
0-
b100 *
b0 )
b0 $
b0 ,
b100 #
b100 +
b100 &
b0 '
#650
b101 !
b101 1
b101 *
b1 $
b1 ,
b1 '
#660
b110 !
b110 1
b110 *
b10 $
b10 ,
b10 '
#670
b111 !
b111 1
b111 *
b11 $
b11 ,
b11 '
#680
1/
b1000 !
b1000 1
b0 *
b100 )
b100 $
b100 ,
b100 '
#690
b1001 !
b1001 1
b1 *
b101 $
b101 ,
b101 '
#700
b1010 !
b1010 1
b10 *
b110 $
b110 ,
b110 '
#710
b1011 !
b1011 1
b11 *
b111 $
b111 ,
b111 '
#720
0/
b1100 !
b1100 1
b1100 *
b0 )
b1000 $
b1000 ,
b1000 '
#730
b1101 !
b1101 1
b1101 *
b1001 $
b1001 ,
b1001 '
#740
b1110 !
b1110 1
b1110 *
b1010 $
b1010 ,
b1010 '
#750
b1111 !
b1111 1
b1111 *
b1011 $
b1011 ,
b1011 '
#760
1"
10
1/
b0 !
b0 1
b1000 *
b100 )
b1100 $
b1100 ,
b1100 '
#770
b1 !
b1 1
b1001 *
b1101 $
b1101 ,
b1101 '
#780
b10 !
b10 1
b1010 *
b1110 $
b1110 ,
b1110 '
#790
b11 !
b11 1
b1011 *
b1111 $
b1111 ,
b1111 '
#800
0"
00
0/
b101 !
b101 1
b101 *
b0 )
b0 $
b0 ,
b101 #
b101 +
b101 &
b0 '
#810
b110 !
b110 1
1-
b100 *
b1 )
b1 $
b1 ,
b1 '
#820
b111 !
b111 1
0-
b111 *
b0 )
b10 $
b10 ,
b10 '
#830
1.
1/
b1000 !
b1000 1
1-
b110 *
b1 )
b11 $
b11 ,
b11 '
#840
0.
b1001 !
b1001 1
0-
b1 *
b100 )
b100 $
b100 ,
b100 '
#850
b1010 !
b1010 1
1-
b0 *
b101 )
b101 $
b101 ,
b101 '
#860
b1011 !
b1011 1
0-
b11 *
b100 )
b110 $
b110 ,
b110 '
#870
1.
b1100 !
b1100 1
1-
b10 *
b101 )
b111 $
b111 ,
b111 '
#880
0.
0/
b1101 !
b1101 1
0-
b1101 *
b0 )
b1000 $
b1000 ,
b1000 '
#890
b1110 !
b1110 1
1-
b1100 *
b1 )
b1001 $
b1001 ,
b1001 '
#900
b1111 !
b1111 1
0-
b1111 *
b0 )
b1010 $
b1010 ,
b1010 '
#910
1.
1/
1"
10
b0 !
b0 1
1-
b1110 *
b1 )
b1011 $
b1011 ,
b1011 '
#920
0.
1"
10
b1 !
b1 1
0-
b1001 *
b100 )
b1100 $
b1100 ,
b1100 '
#930
b10 !
b10 1
1-
b1000 *
b101 )
b1101 $
b1101 ,
b1101 '
#940
b11 !
b11 1
0-
b1011 *
b100 )
b1110 $
b1110 ,
b1110 '
#950
1.
b100 !
b100 1
1-
b1010 *
b101 )
b1111 $
b1111 ,
b1111 '
#960
0"
00
0.
0/
b110 !
b110 1
0-
b110 *
b0 )
b0 $
b0 ,
b110 #
b110 +
b110 &
b0 '
#970
b111 !
b111 1
b111 *
b1 $
b1 ,
b1 '
#980
1/
1.
b1000 !
b1000 1
b100 *
b10 )
b10 $
b10 ,
b10 '
#990
b1001 !
b1001 1
b101 *
b11 $
b11 ,
b11 '
#1000
0.
b1010 !
b1010 1
b10 *
b100 )
b100 $
b100 ,
b100 '
#1010
b1011 !
b1011 1
b11 *
b101 $
b101 ,
b101 '
#1020
1.
b1100 !
b1100 1
b0 *
b110 )
b110 $
b110 ,
b110 '
#1030
b1101 !
b1101 1
b1 *
b111 $
b111 ,
b111 '
#1040
0/
0.
b1110 !
b1110 1
b1110 *
b0 )
b1000 $
b1000 ,
b1000 '
#1050
b1111 !
b1111 1
b1111 *
b1001 $
b1001 ,
b1001 '
#1060
1/
1"
10
1.
b0 !
b0 1
b1100 *
b10 )
b1010 $
b1010 ,
b1010 '
#1070
b1 !
b1 1
b1101 *
b1011 $
b1011 ,
b1011 '
#1080
1"
10
0.
b10 !
b10 1
b1010 *
b100 )
b1100 $
b1100 ,
b1100 '
#1090
b11 !
b11 1
b1011 *
b1101 $
b1101 ,
b1101 '
#1100
1.
b100 !
b100 1
b1000 *
b110 )
b1110 $
b1110 ,
b1110 '
#1110
b101 !
b101 1
b1001 *
b1111 $
b1111 ,
b1111 '
#1120
0"
00
0/
0.
b111 !
b111 1
b111 *
b0 )
b0 $
b0 ,
b111 #
b111 +
b111 &
b0 '
#1130
1.
1/
b1000 !
b1000 1
1-
b110 *
b1 )
b1 $
b1 ,
b1 '
#1140
1/
b1001 !
b1001 1
0-
b101 *
b10 )
b10 $
b10 ,
b10 '
#1150
b1010 !
b1010 1
1-
b100 *
b11 )
b11 $
b11 ,
b11 '
#1160
0.
b1011 !
b1011 1
0-
b11 *
b100 )
b100 $
b100 ,
b100 '
#1170
1.
b1100 !
b1100 1
1-
b10 *
b101 )
b101 $
b101 ,
b101 '
#1180
b1101 !
b1101 1
0-
b1 *
b110 )
b110 $
b110 ,
b110 '
#1190
b1110 !
b1110 1
1-
b0 *
b111 )
b111 $
b111 ,
b111 '
#1200
0/
0.
b1111 !
b1111 1
0-
b1111 *
b0 )
b1000 $
b1000 ,
b1000 '
#1210
1.
1/
1"
10
b0 !
b0 1
1-
b1110 *
b1 )
b1001 $
b1001 ,
b1001 '
#1220
1/
1"
10
b1 !
b1 1
0-
b1101 *
b10 )
b1010 $
b1010 ,
b1010 '
#1230
b10 !
b10 1
1-
b1100 *
b11 )
b1011 $
b1011 ,
b1011 '
#1240
1"
10
0.
b11 !
b11 1
0-
b1011 *
b100 )
b1100 $
b1100 ,
b1100 '
#1250
1.
b100 !
b100 1
1-
b1010 *
b101 )
b1101 $
b1101 ,
b1101 '
#1260
b101 !
b101 1
0-
b1001 *
b110 )
b1110 $
b1110 ,
b1110 '
#1270
b110 !
b110 1
1-
b1000 *
b111 )
b1111 $
b1111 ,
b1111 '
#1280
0"
00
0/
b1000 !
b1000 1
0.
0-
b0 )
b0 $
b0 ,
b1000 #
b1000 +
b1000 &
b0 '
#1290
b1001 !
b1001 1
b1001 *
b1 $
b1 ,
b1 '
#1300
b1010 !
b1010 1
b1010 *
b10 $
b10 ,
b10 '
#1310
b1011 !
b1011 1
b1011 *
b11 $
b11 ,
b11 '
#1320
b1100 !
b1100 1
b1100 *
b100 $
b100 ,
b100 '
#1330
b1101 !
b1101 1
b1101 *
b101 $
b101 ,
b101 '
#1340
b1110 !
b1110 1
b1110 *
b110 $
b110 ,
b110 '
#1350
b1111 !
b1111 1
b1111 *
b111 $
b111 ,
b111 '
#1360
1"
10
b0 !
b0 1
b0 *
b1000 )
b1000 $
b1000 ,
b1000 '
#1370
b1 !
b1 1
b1 *
b1001 $
b1001 ,
b1001 '
#1380
b10 !
b10 1
b10 *
b1010 $
b1010 ,
b1010 '
#1390
b11 !
b11 1
b11 *
b1011 $
b1011 ,
b1011 '
#1400
b100 !
b100 1
b100 *
b1100 $
b1100 ,
b1100 '
#1410
b101 !
b101 1
b101 *
b1101 $
b1101 ,
b1101 '
#1420
b110 !
b110 1
b110 *
b1110 $
b1110 ,
b1110 '
#1430
b111 !
b111 1
b111 *
b1111 $
b1111 ,
b1111 '
#1440
0"
00
b1001 !
b1001 1
b1001 *
b0 )
b0 $
b0 ,
b1001 #
b1001 +
b1001 &
b0 '
#1450
b1010 !
b1010 1
1-
b1000 *
b1 )
b1 $
b1 ,
b1 '
#1460
b1011 !
b1011 1
0-
b1011 *
b0 )
b10 $
b10 ,
b10 '
#1470
1.
b1100 !
b1100 1
1-
b1010 *
b1 )
b11 $
b11 ,
b11 '
#1480
0.
b1101 !
b1101 1
0-
b1101 *
b0 )
b100 $
b100 ,
b100 '
#1490
b1110 !
b1110 1
1-
b1100 *
b1 )
b101 $
b101 ,
b101 '
#1500
b1111 !
b1111 1
0-
b1111 *
b0 )
b110 $
b110 ,
b110 '
#1510
1.
1/
1"
10
b0 !
b0 1
1-
b1110 *
b1 )
b111 $
b111 ,
b111 '
#1520
0.
0/
1"
10
b1 !
b1 1
0-
b1 *
b1000 )
b1000 $
b1000 ,
b1000 '
#1530
b10 !
b10 1
1-
b0 *
b1001 )
b1001 $
b1001 ,
b1001 '
#1540
b11 !
b11 1
0-
b11 *
b1000 )
b1010 $
b1010 ,
b1010 '
#1550
1.
b100 !
b100 1
1-
b10 *
b1001 )
b1011 $
b1011 ,
b1011 '
#1560
0.
b101 !
b101 1
0-
b101 *
b1000 )
b1100 $
b1100 ,
b1100 '
#1570
b110 !
b110 1
1-
b100 *
b1001 )
b1101 $
b1101 ,
b1101 '
#1580
b111 !
b111 1
0-
b111 *
b1000 )
b1110 $
b1110 ,
b1110 '
#1590
1.
1/
b1000 !
b1000 1
1-
b110 *
b1001 )
b1111 $
b1111 ,
b1111 '
#1600
0"
00
0.
0/
b1010 !
b1010 1
0-
b1010 *
b0 )
b0 $
b0 ,
b1010 #
b1010 +
b1010 &
b0 '
#1610
b1011 !
b1011 1
b1011 *
b1 $
b1 ,
b1 '
#1620
1.
b1100 !
b1100 1
b1000 *
b10 )
b10 $
b10 ,
b10 '
#1630
b1101 !
b1101 1
b1001 *
b11 $
b11 ,
b11 '
#1640
0.
b1110 !
b1110 1
b1110 *
b0 )
b100 $
b100 ,
b100 '
#1650
b1111 !
b1111 1
b1111 *
b101 $
b101 ,
b101 '
#1660
1/
1"
10
1.
b0 !
b0 1
b1100 *
b10 )
b110 $
b110 ,
b110 '
#1670
b1 !
b1 1
b1101 *
b111 $
b111 ,
b111 '
#1680
0/
0.
b10 !
b10 1
b10 *
b1000 )
b1000 $
b1000 ,
b1000 '
#1690
b11 !
b11 1
b11 *
b1001 $
b1001 ,
b1001 '
#1700
1.
b100 !
b100 1
b0 *
b1010 )
b1010 $
b1010 ,
b1010 '
#1710
b101 !
b101 1
b1 *
b1011 $
b1011 ,
b1011 '
#1720
0.
b110 !
b110 1
b110 *
b1000 )
b1100 $
b1100 ,
b1100 '
#1730
b111 !
b111 1
b111 *
b1101 $
b1101 ,
b1101 '
#1740
1/
1.
b1000 !
b1000 1
b100 *
b1010 )
b1110 $
b1110 ,
b1110 '
#1750
b1001 !
b1001 1
b101 *
b1111 $
b1111 ,
b1111 '
#1760
0/
0"
00
0.
b1011 !
b1011 1
b1011 *
b0 )
b0 $
b0 ,
b1011 #
b1011 +
b1011 &
b0 '
#1770
1.
b1100 !
b1100 1
1-
b1010 *
b1 )
b1 $
b1 ,
b1 '
#1780
b1101 !
b1101 1
0-
b1001 *
b10 )
b10 $
b10 ,
b10 '
#1790
b1110 !
b1110 1
1-
b1000 *
b11 )
b11 $
b11 ,
b11 '
#1800
0.
b1111 !
b1111 1
0-
b1111 *
b0 )
b100 $
b100 ,
b100 '
#1810
1.
1/
1"
10
b0 !
b0 1
1-
b1110 *
b1 )
b101 $
b101 ,
b101 '
#1820
1/
1"
10
b1 !
b1 1
0-
b1101 *
b10 )
b110 $
b110 ,
b110 '
#1830
b10 !
b10 1
1-
b1100 *
b11 )
b111 $
b111 ,
b111 '
#1840
0/
0.
b11 !
b11 1
0-
b11 *
b1000 )
b1000 $
b1000 ,
b1000 '
#1850
1.
b100 !
b100 1
1-
b10 *
b1001 )
b1001 $
b1001 ,
b1001 '
#1860
b101 !
b101 1
0-
b1 *
b1010 )
b1010 $
b1010 ,
b1010 '
#1870
b110 !
b110 1
1-
b0 *
b1011 )
b1011 $
b1011 ,
b1011 '
#1880
0.
b111 !
b111 1
0-
b111 *
b1000 )
b1100 $
b1100 ,
b1100 '
#1890
1.
1/
b1000 !
b1000 1
1-
b110 *
b1001 )
b1101 $
b1101 ,
b1101 '
#1900
1/
b1001 !
b1001 1
0-
b101 *
b1010 )
b1110 $
b1110 ,
b1110 '
#1910
b1010 !
b1010 1
1-
b100 *
b1011 )
b1111 $
b1111 ,
b1111 '
#1920
0/
0"
00
0.
b1100 !
b1100 1
0-
b1100 *
b0 )
b0 $
b0 ,
b1100 #
b1100 +
b1100 &
b0 '
#1930
b1101 !
b1101 1
b1101 *
b1 $
b1 ,
b1 '
#1940
b1110 !
b1110 1
b1110 *
b10 $
b10 ,
b10 '
#1950
b1111 !
b1111 1
b1111 *
b11 $
b11 ,
b11 '
#1960
1"
10
1/
b0 !
b0 1
b1000 *
b100 )
b100 $
b100 ,
b100 '
#1970
b1 !
b1 1
b1001 *
b101 $
b101 ,
b101 '
#1980
b10 !
b10 1
b1010 *
b110 $
b110 ,
b110 '
#1990
b11 !
b11 1
b1011 *
b111 $
b111 ,
b111 '
#2000
0/
b100 !
b100 1
b100 *
b1000 )
b1000 $
b1000 ,
b1000 '
#2010
b101 !
b101 1
b101 *
b1001 $
b1001 ,
b1001 '
#2020
b110 !
b110 1
b110 *
b1010 $
b1010 ,
b1010 '
#2030
b111 !
b111 1
b111 *
b1011 $
b1011 ,
b1011 '
#2040
1/
b1000 !
b1000 1
b0 *
b1100 )
b1100 $
b1100 ,
b1100 '
#2050
b1001 !
b1001 1
b1 *
b1101 $
b1101 ,
b1101 '
#2060
b1010 !
b1010 1
b10 *
b1110 $
b1110 ,
b1110 '
#2070
b1011 !
b1011 1
b11 *
b1111 $
b1111 ,
b1111 '
#2080
0"
00
0/
b1101 !
b1101 1
b1101 *
b0 )
b0 $
b0 ,
b1101 #
b1101 +
b1101 &
b0 '
#2090
b1110 !
b1110 1
1-
b1100 *
b1 )
b1 $
b1 ,
b1 '
#2100
b1111 !
b1111 1
0-
b1111 *
b0 )
b10 $
b10 ,
b10 '
#2110
1.
1/
1"
10
b0 !
b0 1
1-
b1110 *
b1 )
b11 $
b11 ,
b11 '
#2120
0.
1"
10
b1 !
b1 1
0-
b1001 *
b100 )
b100 $
b100 ,
b100 '
#2130
b10 !
b10 1
1-
b1000 *
b101 )
b101 $
b101 ,
b101 '
#2140
b11 !
b11 1
0-
b1011 *
b100 )
b110 $
b110 ,
b110 '
#2150
1.
b100 !
b100 1
1-
b1010 *
b101 )
b111 $
b111 ,
b111 '
#2160
0.
0/
b101 !
b101 1
0-
b101 *
b1000 )
b1000 $
b1000 ,
b1000 '
#2170
b110 !
b110 1
1-
b100 *
b1001 )
b1001 $
b1001 ,
b1001 '
#2180
b111 !
b111 1
0-
b111 *
b1000 )
b1010 $
b1010 ,
b1010 '
#2190
1.
1/
b1000 !
b1000 1
1-
b110 *
b1001 )
b1011 $
b1011 ,
b1011 '
#2200
0.
b1001 !
b1001 1
0-
b1 *
b1100 )
b1100 $
b1100 ,
b1100 '
#2210
b1010 !
b1010 1
1-
b0 *
b1101 )
b1101 $
b1101 ,
b1101 '
#2220
b1011 !
b1011 1
0-
b11 *
b1100 )
b1110 $
b1110 ,
b1110 '
#2230
1.
b1100 !
b1100 1
1-
b10 *
b1101 )
b1111 $
b1111 ,
b1111 '
#2240
0"
00
0.
0/
b1110 !
b1110 1
0-
b1110 *
b0 )
b0 $
b0 ,
b1110 #
b1110 +
b1110 &
b0 '
#2250
b1111 !
b1111 1
b1111 *
b1 $
b1 ,
b1 '
#2260
1/
1"
10
1.
b0 !
b0 1
b1100 *
b10 )
b10 $
b10 ,
b10 '
#2270
b1 !
b1 1
b1101 *
b11 $
b11 ,
b11 '
#2280
1"
10
0.
b10 !
b10 1
b1010 *
b100 )
b100 $
b100 ,
b100 '
#2290
b11 !
b11 1
b1011 *
b101 $
b101 ,
b101 '
#2300
1.
b100 !
b100 1
b1000 *
b110 )
b110 $
b110 ,
b110 '
#2310
b101 !
b101 1
b1001 *
b111 $
b111 ,
b111 '
#2320
0/
0.
b110 !
b110 1
b110 *
b1000 )
b1000 $
b1000 ,
b1000 '
#2330
b111 !
b111 1
b111 *
b1001 $
b1001 ,
b1001 '
#2340
1/
1.
b1000 !
b1000 1
b100 *
b1010 )
b1010 $
b1010 ,
b1010 '
#2350
b1001 !
b1001 1
b101 *
b1011 $
b1011 ,
b1011 '
#2360
0.
b1010 !
b1010 1
b10 *
b1100 )
b1100 $
b1100 ,
b1100 '
#2370
b1011 !
b1011 1
b11 *
b1101 $
b1101 ,
b1101 '
#2380
1.
b1100 !
b1100 1
b0 *
b1110 )
b1110 $
b1110 ,
b1110 '
#2390
b1101 !
b1101 1
b1 *
b1111 $
b1111 ,
b1111 '
#2400
0"
00
0/
0.
b1111 !
b1111 1
b1111 *
b0 )
b0 $
b0 ,
b1111 #
b1111 +
b1111 &
b0 '
#2410
1.
1/
1"
10
b0 !
b0 1
1-
b1110 *
b1 )
b1 $
b1 ,
b1 '
#2420
1/
1"
10
b1 !
b1 1
0-
b1101 *
b10 )
b10 $
b10 ,
b10 '
#2430
b10 !
b10 1
1-
b1100 *
b11 )
b11 $
b11 ,
b11 '
#2440
1"
10
0.
b11 !
b11 1
0-
b1011 *
b100 )
b100 $
b100 ,
b100 '
#2450
1.
b100 !
b100 1
1-
b1010 *
b101 )
b101 $
b101 ,
b101 '
#2460
b101 !
b101 1
0-
b1001 *
b110 )
b110 $
b110 ,
b110 '
#2470
b110 !
b110 1
1-
b1000 *
b111 )
b111 $
b111 ,
b111 '
#2480
0/
0.
b111 !
b111 1
0-
b111 *
b1000 )
b1000 $
b1000 ,
b1000 '
#2490
1.
1/
b1000 !
b1000 1
1-
b110 *
b1001 )
b1001 $
b1001 ,
b1001 '
#2500
1/
b1001 !
b1001 1
0-
b101 *
b1010 )
b1010 $
b1010 ,
b1010 '
#2510
b1010 !
b1010 1
1-
b100 *
b1011 )
b1011 $
b1011 ,
b1011 '
#2520
0.
b1011 !
b1011 1
0-
b11 *
b1100 )
b1100 $
b1100 ,
b1100 '
#2530
1.
b1100 !
b1100 1
1-
b10 *
b1101 )
b1101 $
b1101 ,
b1101 '
#2540
b1101 !
b1101 1
0-
b1 *
b1110 )
b1110 $
b1110 ,
b1110 '
#2550
b1110 !
b1110 1
1-
b0 *
b1111 )
b1111 $
b1111 ,
b1111 '
#2560
0"
00
0/
0.
0-
b0 )
b1 !
b1 1
b0 $
b0 ,
b0 #
b0 +
1%
b1 (
b0 &
b0 '
#2570
1-
b10 !
b10 1
b1 *
b1 $
b1 ,
b1 '
#2580
0-
b11 !
b11 1
b10 *
b10 $
b10 ,
b10 '
#2590
1.
1-
b100 !
b100 1
b11 *
b11 $
b11 ,
b11 '
#2600
0.
0-
b101 !
b101 1
b100 *
b100 $
b100 ,
b100 '
#2610
1-
b110 !
b110 1
b101 *
b101 $
b101 ,
b101 '
#2620
0-
b111 !
b111 1
b110 *
b110 $
b110 ,
b110 '
#2630
1.
1/
1-
b1000 !
b1000 1
b111 *
b111 $
b111 ,
b111 '
#2640
0.
0/
0-
b1001 !
b1001 1
b1000 *
b1000 $
b1000 ,
b1000 '
#2650
1-
b1010 !
b1010 1
b1001 *
b1001 $
b1001 ,
b1001 '
#2660
0-
b1011 !
b1011 1
b1010 *
b1010 $
b1010 ,
b1010 '
#2670
1.
1-
b1100 !
b1100 1
b1011 *
b1011 $
b1011 ,
b1011 '
#2680
0.
0-
b1101 !
b1101 1
b1100 *
b1100 $
b1100 ,
b1100 '
#2690
1-
b1110 !
b1110 1
b1101 *
b1101 $
b1101 ,
b1101 '
#2700
0-
b1111 !
b1111 1
b1110 *
b1110 $
b1110 ,
b1110 '
#2710
1.
1/
1"
10
1-
b0 !
b0 1
b1111 *
b1111 $
b1111 ,
b1111 '
#2720
0/
0"
00
0.
b10 !
b10 1
b1 *
b0 $
b0 ,
b1 #
b1 +
b1 &
b0 '
#2730
b11 !
b11 1
b0 *
b1 )
b1 $
b1 ,
b1 '
#2740
1.
b100 !
b100 1
1-
b11 *
b0 )
b10 $
b10 ,
b10 '
#2750
b101 !
b101 1
b10 *
b1 )
b11 $
b11 ,
b11 '
#2760
0.
b110 !
b110 1
1-
b101 *
b0 )
b100 $
b100 ,
b100 '
#2770
b111 !
b111 1
b100 *
b1 )
b101 $
b101 ,
b101 '
#2780
1/
1.
b1000 !
b1000 1
1-
b111 *
b0 )
b110 $
b110 ,
b110 '
#2790
b1001 !
b1001 1
b110 *
b1 )
b111 $
b111 ,
b111 '
#2800
0/
0.
b1010 !
b1010 1
1-
b1001 *
b0 )
b1000 $
b1000 ,
b1000 '
#2810
b1011 !
b1011 1
b1000 *
b1 )
b1001 $
b1001 ,
b1001 '
#2820
1.
b1100 !
b1100 1
1-
b1011 *
b0 )
b1010 $
b1010 ,
b1010 '
#2830
b1101 !
b1101 1
b1010 *
b1 )
b1011 $
b1011 ,
b1011 '
#2840
0.
b1110 !
b1110 1
1-
b1101 *
b0 )
b1100 $
b1100 ,
b1100 '
#2850
b1111 !
b1111 1
b1100 *
b1 )
b1101 $
b1101 ,
b1101 '
#2860
1/
1"
10
1.
b0 !
b0 1
1-
b1111 *
b0 )
b1110 $
b1110 ,
b1110 '
#2870
b1 !
b1 1
b1110 *
b1 )
b1111 $
b1111 ,
b1111 '
#2880
0.
0/
0"
00
b11 !
b11 1
0-
b10 *
b0 )
b0 $
b0 ,
b10 #
b10 +
b10 &
b0 '
#2890
1.
1-
b100 !
b100 1
b11 *
b1 $
b1 ,
b1 '
#2900
0-
b101 !
b101 1
b0 *
b10 )
b10 $
b10 ,
b10 '
#2910
1-
b110 !
b110 1
b1 *
b11 $
b11 ,
b11 '
#2920
0-
0.
b111 !
b111 1
b110 *
b0 )
b100 $
b100 ,
b100 '
#2930
1.
1/
1-
b1000 !
b1000 1
b111 *
b101 $
b101 ,
b101 '
