bcd_adder/design.sv
// Code your design here
module half_adder(input x, y, output [1:0]s);
  assign s[0] = x ^ y;
  assign s[1] = x&y;
endmodule



module full_adder(input x, y, cin, output [1:0]sum);
  wire [1:0]p;
  half_adder one(.x(x), .y(y), .s(p));
  
  wire [1:0] q;
  
  half_adder two(.x(p[0]), .y(cin), .s(q));
  
  assign sum[0]=q[0];
  assign sum[1] = p[1]|q[1];
endmodule

  
  

module four_bit_adder(input [3:0]a,b, input cin, output [3:0]finalsum, output cout);
  wire [1:0] p;
  full_adder one(.x(a[0]), .y(b[0]), .cin(cin), .sum(p));
  assign finalsum[0]=p[0];
  
  
  wire [1:0] q;
  full_adder two(.x(a[1]), .y(b[1]), .cin(p[1]), .sum(q));
  assign finalsum[1]=q[0];
  
  wire [1:0] r;
  full_adder three(.x(a[2]), .y(b[2]), .cin(q[1]), .sum(r));
  assign finalsum[2]=r[0];
  
  wire [1:0] s;
  full_adder four(.x(a[3]), .y(b[3]), .cin(r[1]), .sum(s));
  assign finalsum[3]=s[0];
  
  assign cout=s[1];
  
endmodule



module bcd_adder(input [3:0]a, input [3:0]b, input cin, output [3:0]bcdsum, output final_cout);
  wire[3:0] sum1;
  wire k;
  
  four_bit_adder one(.a(a), .b(b), .cin(cin), .finalsum(sum1),.cout(k));
  
  
  
  wire output_carry;
  assign output_carry=k | sum1[3]&sum1[2] | sum1[3] & sum1[1];
  
  
  wire[3:0] sum2;
  wire correction_carry;
 
  
  four_bit_adder two(.a(4'b0110), .b(sum1), .cin(1'b0), .finalsum(sum2),.cout(correction_carry));
  
  assign bcdsum= output_carry ? sum2 : sum1;
  assign final_cout = output_carry;
  
 
endmodule

bcd_adder/testbench.sv
// Code your testbench here
// or browse Examples
module testbench();
  reg [3:0] a;
  reg [3:0] b;
  reg cin;
  
  wire [3:0] sum;
  wire cout;
  
  
  bcd_adder dut(.a(a), .b(b), .cin(cin), .bcdsum(sum), .final_cout(cout));
  
  integer i, j, k;

  initial begin
      for (k = 0; k < 2; k = k + 1) begin
          cin = k;

          for (i = 0; i < 10; i = i + 1) begin
              for (j = 0; j < 10; j = j + 1) begin
                  a = i;
                  b = j;
                  #10;
              end
          end
      end

      $finish;
  end

  initial begin
    $monitor("time=%0t a=%b b=%b cin=%b cout=%b sum=%b",
              $time, a, b, cin, cout, sum);
  end


  initial begin
      $dumpfile("dump.vcd");
      $dumpvars(0, testbench);
  end
  
  
  
endmodule

bcd_adder/dump.vcd
$date
	Mon Jul 20 14:36:05 2026
$end
$version
	Icarus Verilog
$end
$timescale
	1s
$end
$scope module testbench $end
$var wire 4 ! sum [3:0] $end
$var wire 1 " cout $end
$var reg 4 # a [3:0] $end
$var reg 4 $ b [3:0] $end
$var reg 1 % cin $end
$var integer 32 & i [31:0] $end
$var integer 32 ' j [31:0] $end
$var integer 32 ( k [31:0] $end
$scope module dut $end
$var wire 4 ) a [3:0] $end
$var wire 4 * b [3:0] $end
$var wire 1 % cin $end
$var wire 1 " final_cout $end
$var wire 1 + output_carry $end
$var wire 4 , sum2 [3:0] $end
$var wire 4 - sum1 [3:0] $end
$var wire 1 . k $end
$var wire 1 / correction_carry $end
$var wire 4 0 bcdsum [3:0] $end
$scope module one $end
$var wire 4 1 a [3:0] $end
$var wire 4 2 b [3:0] $end
$var wire 1 % cin $end
$var wire 2 3 s [1:0] $end
$var wire 2 4 r [1:0] $end
$var wire 2 5 q [1:0] $end
$var wire 2 6 p [1:0] $end
$var wire 4 7 finalsum [3:0] $end
$var wire 1 . cout $end
$scope module four $end
$var wire 1 8 cin $end
$var wire 1 9 x $end
$var wire 1 : y $end
$var wire 2 ; sum [1:0] $end
$var wire 2 < q [1:0] $end
$var wire 2 = p [1:0] $end
$scope module one $end
$var wire 1 9 x $end
$var wire 1 : y $end
$var wire 2 > s [1:0] $end
$upscope $end
$scope module two $end
$var wire 1 ? x $end
$var wire 1 8 y $end
$var wire 2 @ s [1:0] $end
$upscope $end
$upscope $end
$scope module one $end
$var wire 1 % cin $end
$var wire 1 A x $end
$var wire 1 B y $end
$var wire 2 C sum [1:0] $end
$var wire 2 D q [1:0] $end
$var wire 2 E p [1:0] $end
$scope module one $end
$var wire 1 A x $end
$var wire 1 B y $end
$var wire 2 F s [1:0] $end
$upscope $end
$scope module two $end
$var wire 1 G x $end
$var wire 1 % y $end
$var wire 2 H s [1:0] $end
$upscope $end
$upscope $end
$scope module three $end
$var wire 1 I cin $end
$var wire 1 J x $end
$var wire 1 K y $end
$var wire 2 L sum [1:0] $end
$var wire 2 M q [1:0] $end
$var wire 2 N p [1:0] $end
$scope module one $end
$var wire 1 J x $end
$var wire 1 K y $end
$var wire 2 O s [1:0] $end
$upscope $end
$scope module two $end
$var wire 1 P x $end
$var wire 1 I y $end
$var wire 2 Q s [1:0] $end
$upscope $end
$upscope $end
$scope module two $end
$var wire 1 R cin $end
$var wire 1 S x $end
$var wire 1 T y $end
$var wire 2 U sum [1:0] $end
$var wire 2 V q [1:0] $end
$var wire 2 W p [1:0] $end
$scope module one $end
$var wire 1 S x $end
$var wire 1 T y $end
$var wire 2 X s [1:0] $end
$upscope $end
$scope module two $end
$var wire 1 Y x $end
$var wire 1 R y $end
$var wire 2 Z s [1:0] $end
$upscope $end
$upscope $end
$upscope $end
$scope module two $end
$var wire 4 [ a [3:0] $end
$var wire 4 \ b [3:0] $end
$var wire 1 ] cin $end
$var wire 2 ^ s [1:0] $end
$var wire 2 _ r [1:0] $end
$var wire 2 ` q [1:0] $end
$var wire 2 a p [1:0] $end
$var wire 4 b finalsum [3:0] $end
$var wire 1 / cout $end
$scope module four $end
$var wire 1 c cin $end
$var wire 1 d x $end
$var wire 1 e y $end
$var wire 2 f sum [1:0] $end
$var wire 2 g q [1:0] $end
$var wire 2 h p [1:0] $end
$scope module one $end
$var wire 1 d x $end
$var wire 1 e y $end
$var wire 2 i s [1:0] $end
$upscope $end
$scope module two $end
$var wire 1 j x $end
$var wire 1 c y $end
$var wire 2 k s [1:0] $end
$upscope $end
$upscope $end
$scope module one $end
$var wire 1 ] cin $end
$var wire 1 l x $end
$var wire 1 m y $end
$var wire 2 n sum [1:0] $end
$var wire 2 o q [1:0] $end
$var wire 2 p p [1:0] $end
$scope module one $end
$var wire 1 l x $end
$var wire 1 m y $end
$var wire 2 q s [1:0] $end
$upscope $end
$scope module two $end
$var wire 1 r x $end
$var wire 1 ] y $end
$var wire 2 s s [1:0] $end
$upscope $end
$upscope $end
$scope module three $end
$var wire 1 t cin $end
$var wire 1 u x $end
$var wire 1 v y $end
$var wire 2 w sum [1:0] $end
$var wire 2 x q [1:0] $end
$var wire 2 y p [1:0] $end
$scope module one $end
$var wire 1 u x $end
$var wire 1 v y $end
$var wire 2 z s [1:0] $end
$upscope $end
$scope module two $end
$var wire 1 { x $end
$var wire 1 t y $end
$var wire 2 | s [1:0] $end
$upscope $end
$upscope $end
$scope module two $end
$var wire 1 } cin $end
$var wire 1 ~ x $end
$var wire 1 !" y $end
$var wire 2 "" sum [1:0] $end
$var wire 2 #" q [1:0] $end
$var wire 2 $" p [1:0] $end
$scope module one $end
$var wire 1 ~ x $end
$var wire 1 !" y $end
$var wire 2 %" s [1:0] $end
$upscope $end
$scope module two $end
$var wire 1 &" x $end
$var wire 1 } y $end
$var wire 2 '" s [1:0] $end
$upscope $end
$upscope $end
$upscope $end
$upscope $end
$upscope $end
$enddefinitions $end
$comment Show the parameter values. $end
$dumpall
$end
#0
$dumpvars
b1 '"
1&"
b1 %"
b1 $"
b1 #"
b1 ""
0!"
1~
0}
b1 |
1{
b1 z
b1 y
b1 x
b1 w
0v
1u
0t
b0 s
0r
b0 q
b0 p
b0 o
b0 n
0m
0l
b0 k
0j
b0 i
b0 h
b0 g
b0 f
0e
0d
0c
b110 b
b0 a
b1 `
b1 _
b0 ^
0]
b0 \
b110 [
b0 Z
0Y
b0 X
b0 W
b0 V
b0 U
0T
0S
0R
b0 Q
0P
b0 O
b0 N
b0 M
b0 L
0K
0J
0I
b0 H
0G
b0 F
b0 E
b0 D
b0 C
0B
0A
b0 @
0?
b0 >
b0 =
b0 <
b0 ;
0:
09
08
b0 7
b0 6
b0 5
b0 4
b0 3
b0 2
b0 1
b0 0
0/
0.
b0 -
b110 ,
0+
b0 *
b0 )
b0 (
b0 '
b0 &
0%
b0 $
b0 #
0"
b0 !
$end
#10
b111 ,
b111 b
b1 a
b1 n
b1 o
b1 s
1r
b1 p
b1 q
1m
b1 !
b1 0
b1 -
b1 7
b1 \
b1 6
b1 C
b1 D
b1 H
1G
b1 E
b1 F
1B
b1 $
b1 *
b1 2
b1 '
#20
b1 ^
b1 f
b1 g
b1 k
1c
b10 _
b10 w
b1000 ,
b1000 b
b10 x
b10 |
b0 a
b0 n
1t
b0 o
b0 s
b0 #"
b0 '"
b10 `
b10 ""
0r
0&"
b0 p
b0 q
b10 $"
b10 %"
0m
1!"
b10 !
b10 0
b10 -
b10 7
b10 \
b0 6
b0 C
b1 5
b1 U
b0 D
b0 H
b1 V
b1 Z
0G
1Y
b0 E
b0 F
b1 W
b1 X
0B
1T
b10 $
b10 *
b10 2
b10 '
#30
b1001 ,
b1001 b
b1 a
b1 n
b1 o
b1 s
1r
b1 p
b1 q
1m
b11 !
b11 0
b11 -
b11 7
b11 \
b1 6
b1 C
b1 D
b1 H
1G
b1 E
b1 F
1B
b11 $
b11 *
b11 2
b11 '
#40
b1010 ,
b1010 b
b0 a
b0 n
0t
b10 _
b10 w
b0 o
b0 s
b1 #"
b1 '"
b1 `
b1 ""
b0 x
b0 |
0r
1&"
0{
b0 p
b0 q
b1 $"
b1 %"
b10 y
b10 z
0m
0!"
1v
b100 !
b100 0
b100 -
b100 7
b100 \
b0 6
b0 C
b0 5
b0 U
b1 4
b1 L
b0 D
b0 H
b0 V
b0 Z
b1 M
b1 Q
0G
0Y
1P
b0 E
b0 F
b0 W
b0 X
b1 N
b1 O
0B
0T
1K
b100 $
b100 *
b100 2
b100 '
#50
b1011 ,
b1011 b
b1 a
b1 n
b1 o
b1 s
1r
b1 p
b1 q
1m
b101 !
b101 0
b101 -
b101 7
b101 \
b1 6
b1 C
b1 D
b1 H
1G
b1 E
b1 F
1B
b101 $
b101 *
b101 2
b101 '
#60
b11 _
b11 w
b1100 ,
b1100 b
b1 x
b1 |
b0 a
b0 n
1t
b0 o
b0 s
b0 #"
b0 '"
b10 `
b10 ""
0r
0&"
b0 p
b0 q
b10 $"
b10 %"
0m
1!"
b110 !
b110 0
b110 -
b110 7
b110 \
b0 6
b0 C
b1 5
b1 U
b0 D
b0 H
b1 V
b1 Z
0G
1Y
b0 E
b0 F
b1 W
b1 X
0B
1T
b110 $
b110 *
b110 2
b110 '
#70
b1101 ,
b1101 b
b1 a
b1 n
b1 o
b1 s
1r
b1 p
b1 q
1m
b111 !
b111 0
b111 -
b111 7
b111 \
b1 6
b1 C
b1 D
b1 H
1G
b1 E
b1 F
1B
b111 $
b111 *
b111 2
b111 '
#80
0/
b1110 ,
b1110 b
b0 a
b0 n
0t
0c
b1 ^
b1 f
b0 o
b0 s
b1 #"
b1 '"
b1 `
b1 ""
b1 x
b1 |
b1 _
b1 w
b1 g
b1 k
0r
1&"
1{
1j
b0 p
b0 q
b1 $"
b1 %"
b1 y
b1 z
b1 h
b1 i
0m
0!"
0v
1e
b1000 !
b1000 0
b1000 -
b1000 7
b1000 \
b0 6
b0 C
b0 5
b0 U
b0 4
b0 L
b1 3
b1 ;
b0 D
b0 H
b0 V
b0 Z
b0 M
b0 Q
b1 <
b1 @
0G
0Y
0P
1?
b0 E
b0 F
b0 W
b0 X
b0 N
b0 O
b1 =
b1 >
0B
0T
0K
1:
b1000 $
b1000 *
b1000 2
b1000 '
#90
b1111 ,
b1111 b
b1 a
b1 n
b1 o
b1 s
1r
b1 p
b1 q
1m
b1001 !
b1001 0
b1001 -
b1001 7
b1001 \
b1 6
b1 C
b1 D
b1 H
1G
b1 E
b1 F
1B
b1001 $
b1001 *
b1001 2
b1001 '
#100
b111 ,
b111 b
b0 ^
b0 f
b0 g
b0 k
0j
b0 h
b0 i
0e
b1 !
b1 0
b1 -
b1 7
b1 \
b0 3
b0 ;
b0 <
b0 @
0?
b0 =
b0 >
0B
0:
1A
b0 $
b0 *
b0 2
b1 #
b1 )
b1 1
b1 &
b0 '
#110
b1 ^
b1 f
b1 g
b1 k
1c
b10 _
b10 w
b10 x
b10 |
1t
b1000 ,
b1000 b
b0 #"
b0 '"
b10 `
b10 ""
b0 a
b0 n
0&"
b0 o
b0 s
b10 $"
b10 %"
0r
1!"
b0 p
b0 q
0m
b10 !
b10 0
b1 5
b1 U
b10 -
b10 7
b10 \
b1 V
b1 Z
1R
b0 D
b0 H
b10 6
b10 C
0G
b10 E
b10 F
1B
b1 $
b1 *
b1 2
b1 '
#120
b1 ^
b1 f
b1 g
b1 k
1c
b10 _
b10 w
1{
b1001 ,
b1001 b
b10 x
b10 |
b1 y
b1 z
b1 a
b1 n
1t
0v
b1 o
b1 s
b0 #"
b0 '"
b10 `
b10 ""
1r
0&"
b0 4
b0 L
b1 p
b1 q
b10 $"
b10 %"
b0 M
b0 Q
1m
1!"
b11 !
b11 0
0I
b11 -
b11 7
b11 \
0R
b1 5
b1 U
b1 D
b1 H
b1 6
b1 C
b1 V
b1 Z
1G
1Y
b1 E
b1 F
b1 W
b1 X
0B
1T
b10 $
b10 *
b10 2
b10 '
#130
b10 _
b10 w
0{
b0 x
b0 |
b10 y
b10 z
0t
1v
b1010 ,
b1010 b
b1 #"
b1 '"
b1 `
b1 ""
b0 a
b0 n
1&"
b1 4
b1 L
b0 o
b0 s
b1 $"
b1 %"
b1 M
b1 Q
0r
0!"
1I
b0 p
b0 q
0m
b100 !
b100 0
b10 5
b10 U
b100 -
b100 7
b100 \
b10 V
b10 Z
1R
b0 D
b0 H
b10 6
b10 C
0G
b10 E
b10 F
1B
b11 $
b11 *
b11 2
b11 '
#140
0/
0"
0+
b1 ^
b1 f
0j
b1011 ,
b1011 b
b1 g
b1 k
b0 h
b0 i
b1 a
b1 n
0t
1c
0e
b1 o
b1 s
b1 #"
b1 '"
b1 `
b1 ""
b0 x
b0 |
b10 _
b10 w
1r
1&"
0{
b0 3
b0 ;
b1 p
b1 q
b1 $"
b1 %"
b10 y
b10 z
b0 <
b0 @
1m
0!"
0I
1v
b101 !
b101 0
08
b101 -
b101 7
b101 \
0R
b0 5
b0 U
b1 4
b1 L
b1 D
b1 H
b1 6
b1 C
b0 V
b0 Z
b1 M
b1 Q
1G
0Y
1P
b1 E
b1 F
b0 W
b0 X
b1 N
b1 O
0B
0T
1K
b100 $
b100 *
b100 2
b100 '
#150
b11 _
b11 w
b1 x
b1 |
1t
b1100 ,
b1100 b
b0 #"
b0 '"
b10 `
b10 ""
b0 a
b0 n
0&"
b0 o
b0 s
b10 $"
b10 %"
0r
1!"
b0 p
b0 q
0m
b110 !
b110 0
b1 5
b1 U
b110 -
b110 7
b110 \
b1 V
b1 Z
1R
b0 D
b0 H
b10 6
b10 C
0G
b10 E
b10 F
1B
b101 $
b101 *
b101 2
b101 '
#160
0/
b1 ^
b1 f
0j
0"
0+
b1 g
b1 k
b0 h
b0 i
1c
0e
b11 _
b11 w
0{
b0 3
b0 ;
b1101 ,
b1101 b
b1 x
b1 |
b10 y
b10 z
b0 <
b0 @
b1 a
b1 n
1t
1v
08
b1 o
b1 s
b0 #"
b0 '"
b10 `
b10 ""
1r
0&"
b1 4
b1 L
b1 p
b1 q
b10 $"
b10 %"
b1 M
b1 Q
1m
1!"
b111 !
b111 0
0I
b111 -
b111 7
b111 \
0R
b1 5
b1 U
b1 D
b1 H
b1 6
b1 C
b1 V
b1 Z
1G
1Y
b1 E
b1 F
b1 W
b1 X
0B
1T
b110 $
b110 *
b110 2
b110 '
#170
b1 ^
b1 f
1j
b1 g
b1 k
b1 h
b1 i
0c
1e
b1 _
b1 w
1{
b1 3
b1 ;
b1 x
b1 |
b1 y
b1 z
b1 <
b1 @
0t
0v
18
b1110 ,
b1110 b
b1 #"
b1 '"
b1 `
b1 ""
b0 a
b0 n
1&"
b10 4
b10 L
b0 o
b0 s
b1 $"
b1 %"
b10 M
b10 Q
0r
0!"
1I
b0 p
b0 q
0m
b1000 !
b1000 0
b10 5
b10 U
b1000 -
b1000 7
b1000 \
b10 V
b10 Z
1R
b0 D
b0 H
b10 6
b10 C
0G
b10 E
b10 F
1B
b111 $
b111 *
b111 2
b111 '
#180
0/
b1111 ,
b1111 b
b1 a
b1 n
0t
0c
b1 ^
b1 f
b1 o
b1 s
b1 #"
b1 '"
b1 `
b1 ""
b1 x
b1 |
b1 _
b1 w
b1 g
b1 k
1r
1&"
1{
1j
0"
0+
b1 p
b1 q
b1 $"
b1 %"
b1 y
b1 z
b1 h
b1 i
1m
0!"
0I
0v
08
1e
b1001 !
b1001 0
0.
b1001 -
b1001 7
b1001 \
0R
b0 5
b0 U
b0 4
b0 L
b1 3
b1 ;
b1 D
b1 H
b1 6
b1 C
b0 V
b0 Z
b0 M
b0 Q
b1 <
b1 @
1G
0Y
0P
1?
b1 E
b1 F
b0 W
b0 X
b0 N
b0 O
b1 =
b1 >
0B
0T
0K
1:
b1000 $
b1000 *
b1000 2
b1000 '
#190
1/
b10 ^
b10 f
b10 g
b10 k
1c
b10 _
b10 w
b10 x
b10 |
1t
b0 ,
b0 b
b0 #"
b0 '"
b10 `
b10 ""
b0 a
b0 n
0&"
1"
1+
b0 o
b0 s
b10 $"
b10 %"
0r
1!"
b0 p
b0 q
0m
b0 !
b0 0
b1 5
b1 U
b1010 -
b1010 7
b1010 \
b1 V
b1 Z
1R
b0 D
b0 H
b10 6
b10 C
0G
b10 E
b10 F
1B
b1001 $
b1001 *
b1001 2
b1001 '
#200
1c
0/
b10 _
b10 w
1{
b1000 ,
b1000 b
b10 x
b10 |
b1 y
b1 z
b1 ^
b1 f
1t
0v
b1 g
b1 k
b0 #"
b0 '"
b10 `
b10 ""
b10 !
b10 0
0j
0&"
0"
0+
b0 4
b0 L
b0 h
b0 i
b10 $"
b10 %"
b0 M
b0 Q
0e
1!"
0I
b10 -
b10 7
b10 \
b0 3
b0 ;
0R
b1 5
b1 U
b0 <
b0 @
b0 6
b0 C
b1 V
b1 Z
0?
1Y
b0 =
b0 >
b0 E
b0 F
b1 W
b1 X
0B
0:
0A
1S
b0 $
b0 *
b0 2
b10 #
b10 )
b10 1
b10 &
b0 '
#210
b1001 ,
b1001 b
b1 a
b1 n
b1 o
b1 s
1r
b1 p
b1 q
1m
b11 !
b11 0
b11 -
b11 7
b11 \
b1 6
b1 C
b1 D
b1 H
1G
b1 E
b1 F
1B
b1 $
b1 *
b1 2
b1 '
#220
b1010 ,
b1010 b
b0 x
b0 |
b0 a
b0 n
0t
0{
b0 o
b0 s
b1 #"
b1 '"
b1 `
b1 ""
b10 y
b10 z
0r
1&"
1v
b0 p
b0 q
b1 $"
b1 %"
0m
0!"
b100 !
b100 0
b1 4
b1 L
b100 -
b100 7
b100 \
b1 M
b1 Q
b0 6
b0 C
1I
b0 D
b0 H
b0 V
b0 Z
b10 5
b10 U
0G
0Y
b0 E
b0 F
b10 W
b10 X
0B
1T
b10 $
b10 *
b10 2
b10 '
#230
b1011 ,
b1011 b
b1 a
b1 n
b1 o
b1 s
1r
b1 p
b1 q
1m
b101 !
b101 0
b101 -
b101 7
b101 \
b1 6
b1 C
b1 D
b1 H
1G
b1 E
b1 F
1B
b11 $
b11 *
b11 2
b11 '
#240
0/
b1 ^
b1 f
0j
0"
0+
b1100 ,
b1100 b
b1 g
b1 k
b0 h
b0 i
b0 a
b0 n
1t
1c
0e
b0 o
b0 s
b0 #"
b0 '"
b10 `
b10 ""
b1 x
b1 |
b11 _
b11 w
0r
0&"
0{
b0 3
b0 ;
b0 p
b0 q
b10 $"
b10 %"
b10 y
b10 z
b0 <
b0 @
0m
1!"
1v
b110 !
b110 0
08
b110 -
b110 7
b110 \
b0 6
b0 C
0I
b1 4
b1 L
b0 D
b0 H
b1 V
b1 Z
b1 5
b1 U
b1 M
b1 Q
0G
1Y
1P
b0 E
b0 F
b1 W
b1 X
b1 N
b1 O
0B
0T
1K
b100 $
b100 *
b100 2
b100 '
#250
b1101 ,
b1101 b
b1 a
b1 n
b1 o
b1 s
1r
b1 p
b1 q
1m
b111 !
b111 0
b111 -
b111 7
b111 \
b1 6
b1 C
b1 D
b1 H
1G
b1 E
b1 F
1B
b101 $
b101 *
b101 2
b101 '
#260
b1 ^
b1 f
1j
b1 g
b1 k
b1 h
b1 i
0c
1e
b1110 ,
b1110 b
b1 _
b1 w
b0 a
b0 n
0t
1{
b1 3
b1 ;
b0 o
b0 s
b1 #"
b1 '"
b1 `
b1 ""
b1 y
b1 z
b1 <
b1 @
0r
1&"
0v
18
b0 p
b0 q
b1 $"
b1 %"
0m
0!"
b1000 !
b1000 0
b10 4
b10 L
b1000 -
b1000 7
b1000 \
b10 M
b10 Q
b0 6
b0 C
1I
b0 D
b0 H
b0 V
b0 Z
b10 5
b10 U
0G
0Y
b0 E
b0 F
b10 W
b10 X
0B
1T
b110 $
b110 *
b110 2
b110 '
#270
b1111 ,
b1111 b
b1 a
b1 n
b1 o
b1 s
1r
b1 p
b1 q
1m
b1001 !
b1001 0
b1001 -
b1001 7
b1001 \
b1 6
b1 C
b1 D
b1 H
1G
b1 E
b1 F
1B
b111 $
b111 *
b111 2
b111 '
#280
1/
b0 ,
b0 b
b0 a
b0 n
1t
1c
b10 ^
b10 f
b0 o
b0 s
b0 #"
b0 '"
b10 `
b10 ""
b10 x
b10 |
b10 _
b10 w
b10 g
b10 k
0r
0&"
1{
1j
1"
1+
b0 p
b0 q
b10 $"
b10 %"
b1 y
b1 z
b1 h
b1 i
0m
1!"
0v
08
1e
b0 !
b0 0
0.
b1010 -
b1010 7
b1010 \
b0 6
b0 C
0I
b0 4
b0 L
b1 3
b1 ;
b0 D
b0 H
b1 V
b1 Z
b1 5
b1 U
b0 M
b0 Q
b1 <
b1 @
0G
1Y
0P
1?
b0 E
b0 F
b1 W
b1 X
b0 N
b0 O
b1 =
b1 >
0B
0T
0K
1:
b1000 $
b1000 *
b1000 2
b1000 '
#290
b1 !
b1 0
b1 ,
b1 b
b1 a
b1 n
b1 o
b1 s
1r
b1 p
b1 q
1m
b1011 -
b1011 7
b1011 \
b1 6
b1 C
b1 D
b1 H
1G
b1 E
b1 F
1B
b1001 $
b1001 *
b1001 2
b1001 '
#300
0/
b1001 ,
b1001 b
b1 ^
b1 f
b1 g
b1 k
b11 !
b11 0
0j
0"
0+
b0 h
b0 i
0e
b11 -
b11 7
b11 \
b0 3
b0 ;
b0 <
b0 @
0?
b0 =
b0 >
0B
0:
1A
b0 $
b0 *
b0 2
b11 #
b11 )
b11 1
b11 &
b0 '
#310
b10 _
b10 w
0{
b0 x
b0 |
b10 y
b10 z
0t
1v
b1010 ,
b1010 b
b1 #"
b1 '"
b1 `
b1 ""
b0 a
b0 n
1&"
b1 4
b1 L
b0 o
b0 s
b1 $"
b1 %"
b1 M
b1 Q
0r
0!"
1I
b0 p
b0 q
0m
b100 !
b100 0
b10 5
b10 U
b100 -
b100 7
b100 \
b10 V
b10 Z
1R
b0 D
b0 H
b10 6
b10 C
0G
b10 E
b10 F
1B
b1 $
b1 *
b1 2
b1 '
#320
b10 _
b10 w
b1011 ,
b1011 b
b0 x
b0 |
b1 a
b1 n
0t
b1 o
b1 s
b1 #"
b1 '"
b1 `
b1 ""
1r
1&"
b1 p
b1 q
b1 $"
b1 %"
1m
0!"
b101 !
b101 0
b101 -
b101 7
b101 \
0R
b10 5
b10 U
b1 D
b1 H
b1 6
b1 C
b0 V
b0 Z
1G
0Y
b1 E
b1 F
b10 W
b10 X
0B
1T
b10 $
b10 *
b10 2
b10 '
#330
b11 _
b11 w
b1 x
b1 |
1t
b1100 ,
b1100 b
b0 #"
b0 '"
b10 `
b10 ""
b0 a
b0 n
0&"
b0 o
b0 s
b10 $"
b10 %"
0r
1!"
b0 p
b0 q
0m
b110 !
b110 0
b11 5
b11 U
b110 -
b110 7
b110 \
b1 V
b1 Z
1R
b0 D
b0 H
b10 6
b10 C
0G
b10 E
b10 F
1B
b11 $
b11 *
b11 2
b11 '
#340
0/
b1 ^
b1 f
0j
0"
0+
b1101 ,
b1101 b
b1 g
b1 k
b0 h
b0 i
b1 a
b1 n
1t
1c
0e
b1 o
b1 s
b0 #"
b0 '"
b10 `
b10 ""
b1 x
b1 |
b11 _
b11 w
1r
0&"
0{
b0 3
b0 ;
b1 p
b1 q
b10 $"
b10 %"
b10 y
b10 z
b0 <
b0 @
1m
1!"
1v
b111 !
b111 0
08
b111 -
b111 7
b111 \
0R
0I
b1 4
b1 L
b1 D
b1 H
b1 6
b1 C
b1 V
b1 Z
b1 5
b1 U
b1 M
b1 Q
1G
1Y
1P
b1 E
b1 F
b1 W
b1 X
b1 N
b1 O
0B
0T
1K
b100 $
b100 *
b100 2
b100 '
#350
b1 ^
b1 f
1j
b1 g
b1 k
b1 h
b1 i
0c
1e
b1 _
b1 w
1{
b1 3
b1 ;
b1 x
b1 |
b1 y
b1 z
b1 <
b1 @
0t
0v
18
b1110 ,
b1110 b
b1 #"
b1 '"
b1 `
b1 ""
b0 a
b0 n
1&"
b10 4
b10 L
b0 o
b0 s
b1 $"
b1 %"
b10 M
b10 Q
0r
0!"
1I
b0 p
b0 q
0m
b1000 !
b1000 0
b10 5
b10 U
b1000 -
b1000 7
b1000 \
b10 V
b10 Z
1R
b0 D
b0 H
b10 6
b10 C
0G
b10 E
b10 F
1B
b101 $
b101 *
b101 2
b101 '
#360
0/
b1 ^
b1 f
b1 g
b1 k
0c
b1 _
b1 w
b1111 ,
b1111 b
b1 x
b1 |
b1 a
b1 n
0t
b1 o
b1 s
b1 #"
b1 '"
b1 `
b1 ""
1r
1&"
0"
0+
b1 p
b1 q
b1 $"
b1 %"
1m
0!"
b1001 !
b1001 0
b1001 -
b1001 7
b1001 \
0R
b10 5
b10 U
b1 D
b1 H
b1 6
b1 C
b0 V
b0 Z
1G
0Y
b1 E
b1 F
b10 W
b10 X
0B
1T
b110 $
b110 *
b110 2
b110 '
#370
1/
b10 ^
b10 f
b10 g
b10 k
1c
b10 _
b10 w
b10 x
b10 |
1t
b0 ,
b0 b
b0 #"
b0 '"
b10 `
b10 ""
b0 a
b0 n
0&"
1"
1+
b0 o
b0 s
b10 $"
b10 %"
0r
1!"
b0 p
b0 q
0m
b0 !
b0 0
b11 5
b11 U
b1010 -
b1010 7
b1010 \
b1 V
b1 Z
1R
b0 D
b0 H
b10 6
b10 C
0G
b10 E
b10 F
1B
b111 $
b111 *
b111 2
b111 '
#380
1c
b1 !
b1 0
1/
b1 ,
b1 b
b1 a
b1 n
1t
b10 _
b10 w
b10 ^
b10 f
b1 o
b1 s
b0 #"
b0 '"
b10 `
b10 ""
b10 x
b10 |
b10 g
b10 k
1r
0&"
1{
1j
b1 p
b1 q
b10 $"
b10 %"
b1 y
b1 z
b1 h
b1 i
1m
1!"
0v
08
1e
0.
b1011 -
b1011 7
b1011 \
0R
0I
b0 4
b0 L
b1 3
b1 ;
b1 D
b1 H
b1 6
b1 C
b1 V
b1 Z
b1 5
b1 U
b0 M
b0 Q
b1 <
b1 @
1G
1Y
0P
1?
b1 E
b1 F
b1 W
b1 X
b0 N
b0 O
b1 =
b1 >
0B
0T
0K
1:
b1000 $
b1000 *
b1000 2
b1000 '
#390
b10 _
b10 w
0{
b0 x
b0 |
b10 y
b10 z
0t
1v
b10 ,
b10 b
b1 #"
b1 '"
b1 `
b1 ""
b10 !
b10 0
b0 a
b0 n
1&"
1"
1+
b1 4
b1 L
b0 o
b0 s
b1 $"
b1 %"
b1 M
b1 Q
0r
0!"
1I
b0 p
b0 q
0m
b10 5
b10 U
b1100 -
b1100 7
b1100 \
b10 V
b10 Z
1R
b0 D
b0 H
b10 6
b10 C
0G
b10 E
b10 F
1B
b1001 $
b1001 *
b1001 2
b1001 '
#400
0/
b1010 ,
b1010 b
b1 ^
b1 f
0t
1c
b100 !
b100 0
b1 g
b1 k
b1 #"
b1 '"
b1 `
b1 ""
b0 x
b0 |
b10 _
b10 w
0"
0+
0j
1&"
0{
b0 h
b0 i
b1 $"
b1 %"
b10 y
b10 z
0e
0!"
0I
1v
08
b100 -
b100 7
b100 \
b0 3
b0 ;
0R
b0 5
b0 U
b1 4
b1 L
b0 <
b0 @
b0 6
b0 C
b0 V
b0 Z
b1 M
b1 Q
0?
0Y
1P
b0 =
b0 >
b0 E
b0 F
b0 W
b0 X
b1 N
b1 O
0B
0:
0A
0S
1J
b0 $
b0 *
b0 2
b100 #
b100 )
b100 1
b100 &
b0 '
#410
b1011 ,
b1011 b
b1 a
b1 n
b1 o
b1 s
1r
b1 p
b1 q
1m
b101 !
b101 0
b101 -
b101 7
b101 \
b1 6
b1 C
b1 D
b1 H
1G
b1 E
b1 F
1B
b1 $
b1 *
b1 2
b1 '
#420
b11 _
b11 w
b1100 ,
b1100 b
b1 x
b1 |
b0 a
b0 n
1t
b0 o
b0 s
b0 #"
b0 '"
b10 `
b10 ""
0r
0&"
b0 p
b0 q
b10 $"
b10 %"
0m
1!"
b110 !
b110 0
b110 -
b110 7
b110 \
b0 6
b0 C
b1 5
b1 U
b0 D
b0 H
b1 V
b1 Z
0G
1Y
b0 E
b0 F
b1 W
b1 X
0B
1T
b10 $
b10 *
b10 2
b10 '
#430
b1101 ,
b1101 b
b1 a
b1 n
b1 o
b1 s
1r
b1 p
b1 q
1m
b111 !
b111 0
b111 -
b111 7
b111 \
b1 6
b1 C
b1 D
b1 H
1G
b1 E
b1 F
1B
b11 $
b11 *
b11 2
b11 '
