4_bit_adder_subtractor/design.sv
// Code your design here
module half_adder(input x, y, output [1:0]s);
  assign s[0] = x ^ y;
  assign s[1] = x&y;
endmodule



module full_adder(input x, y, cin, output [1:0]sum);
  wire [1:0]p;
  half_adder one(.x(x), .y(y), .s(p));
  
  wire [1:0] q;
  
  half_adder two(.x(p[0]), .y(cin), .s(q));
  
  assign sum[0]=q[0];
  assign sum[1] = p[1]|q[1];
endmodule

  
//performs A+B or A-B

module four_bit_adder(input [3:0]a,b, input cin, output [3:0]finalsum, output cout, v);
  wire [1:0] p;
  full_adder one(.x(a[0]), .y(b[0] ^ cin), .cin(cin), .sum(p));
  assign finalsum[0]=p[0];
  
  
  wire [1:0] q;
  full_adder two(.x(a[1]), .y(b[1] ^ cin), .cin(p[1]), .sum(q));
  assign finalsum[1]=q[0];
  
  wire [1:0] r;
  full_adder three(.x(a[2]), .y(b[2] ^ cin), .cin(q[1]), .sum(r));
  assign finalsum[2]=r[0];
  
  wire [1:0] s;
  full_adder four(.x(a[3]), .y(b[3] ^ cin), .cin(r[1]), .sum(s));
  assign finalsum[3]=s[0];
  
  assign cout=s[1];
  
  assign v= cout ^ r[1]; //to check for overflow
  
endmodule

4_bit_adder_subtractor/testbench.sv
// Code your testbench here
// or browse Examples
module testbench();
  reg [3:0] a;
  reg [3:0] b;
  reg cin;
  
  wire [3:0] sum;
  wire cout, v;
  
  
  four_bit_adder dut(.a(a), .b(b), .cin(cin), .finalsum(sum), .cout(cout), .v(v) );
  
  reg clk;
  reg rst;
  
  initial begin
    rst=1;
    clk=0;
    #20
    rst=0;
  end
  
  always begin
    #10
    clk=~clk;
  end
  
  integer i;
  initial begin
    i=0;
  end
  
  
  always@(posedge clk or posedge rst) begin
    if(rst) begin
      i<=0;
      {a,b,cin}<=0;
      
    end
    else begin
      {a,b,cin}<=i;
      if(i==511) begin
        #10;
        $finish;
      end
      else begin
        i<=i+1;
      end
        
    end
  end
  
  
  initial begin
    $monitor("time=%0t a=%b b=%b cin=%b sum=%b cout=%b v=%b",
          $time, a, b, cin, sum, cout, v);
  end


  initial begin
      $dumpfile("dump.vcd");
      $dumpvars(0, testbench);
  end
  
  
  
endmodule

4_bit_adder_subtractor/dump.vcd
$date
	Mon Jul 20 12:01:00 2026
$end
$version
	Icarus Verilog
$end
$timescale
	1s
$end
$scope module testbench $end
$var wire 1 ! v $end
$var wire 4 " sum [3:0] $end
$var wire 1 # cout $end
$var reg 4 $ a [3:0] $end
$var reg 4 % b [3:0] $end
$var reg 1 & cin $end
$var reg 1 ' clk $end
$var reg 1 ( rst $end
$var integer 32 ) i [31:0] $end
$scope module dut $end
$var wire 4 * a [3:0] $end
$var wire 4 + b [3:0] $end
$var wire 1 & cin $end
$var wire 1 ! v $end
$var wire 2 , s [1:0] $end
$var wire 2 - r [1:0] $end
$var wire 2 . q [1:0] $end
$var wire 2 / p [1:0] $end
$var wire 4 0 finalsum [3:0] $end
$var wire 1 # cout $end
$scope module four $end
$var wire 1 1 cin $end
$var wire 1 2 x $end
$var wire 1 3 y $end
$var wire 2 4 sum [1:0] $end
$var wire 2 5 q [1:0] $end
$var wire 2 6 p [1:0] $end
$scope module one $end
$var wire 1 2 x $end
$var wire 1 3 y $end
$var wire 2 7 s [1:0] $end
$upscope $end
$scope module two $end
$var wire 1 8 x $end
$var wire 1 1 y $end
$var wire 2 9 s [1:0] $end
$upscope $end
$upscope $end
$scope module one $end
$var wire 1 & cin $end
$var wire 1 : x $end
$var wire 1 ; y $end
$var wire 2 < sum [1:0] $end
$var wire 2 = q [1:0] $end
$var wire 2 > p [1:0] $end
$scope module one $end
$var wire 1 : x $end
$var wire 1 ; y $end
$var wire 2 ? s [1:0] $end
$upscope $end
$scope module two $end
$var wire 1 @ x $end
$var wire 1 & y $end
$var wire 2 A s [1:0] $end
$upscope $end
$upscope $end
$scope module three $end
$var wire 1 B cin $end
$var wire 1 C x $end
$var wire 1 D y $end
$var wire 2 E sum [1:0] $end
$var wire 2 F q [1:0] $end
$var wire 2 G p [1:0] $end
$scope module one $end
$var wire 1 C x $end
$var wire 1 D y $end
$var wire 2 H s [1:0] $end
$upscope $end
$scope module two $end
$var wire 1 I x $end
$var wire 1 B y $end
$var wire 2 J s [1:0] $end
$upscope $end
$upscope $end
$scope module two $end
$var wire 1 K cin $end
$var wire 1 L x $end
$var wire 1 M y $end
$var wire 2 N sum [1:0] $end
$var wire 2 O q [1:0] $end
$var wire 2 P p [1:0] $end
$scope module one $end
$var wire 1 L x $end
$var wire 1 M y $end
$var wire 2 Q s [1:0] $end
$upscope $end
$scope module two $end
$var wire 1 R x $end
$var wire 1 K y $end
$var wire 2 S s [1:0] $end
$upscope $end
$upscope $end
$upscope $end
$upscope $end
$enddefinitions $end
$comment Show the parameter values. $end
$dumpall
$end
#0
$dumpvars
bx S
xR
bx Q
bx P
bx O
bx N
xM
xL
xK
bx J
xI
bx H
bx G
bx F
bx E
xD
xC
xB
bx A
x@
bx ?
bx >
bx =
bx <
x;
x:
bx 9
x8
bx 7
bx 6
bx 5
bx 4
x3
x2
x1
bx 0
bx /
bx .
bx -
bx ,
bx +
bx *
b0 )
1(
0'
x&
bx %
bx $
x#
bx "
x!
$end
#10
0!
0B
01
0#
b0 "
b0 0
b0 .
b0 N
b0 -
b0 E
b0 ,
b0 4
0K
b0 /
b0 <
b0 O
b0 S
b0 F
b0 J
b0 5
b0 9
0@
0R
0I
08
b0 >
b0 ?
b0 P
b0 Q
b0 G
b0 H
b0 6
b0 7
0;
0M
0D
03
0:
0L
0C
02
b0 =
b0 A
b0 $
b0 *
b0 %
b0 +
0&
1'
#20
0'
0(
#30
b1 )
1'
#40
0'
#50
1#
0!
11
1B
1K
b10 .
b10 N
b10 -
b10 E
b10 ,
b10 4
b10 O
b10 S
b10 F
b10 J
b10 5
b10 9
1@
1R
1I
18
b0 "
b0 0
b1 >
b1 ?
b1 P
b1 Q
b1 G
b1 H
b1 6
b1 7
b10 /
b10 <
1;
1M
1D
13
b10 =
b10 A
b10 )
1&
1'
#60
0'
#70
0B
01
0#
b0 .
b0 N
b0 -
b0 E
b0 ,
b0 4
b0 O
b0 S
b0 F
b0 J
b0 5
b0 9
0K
1@
0R
0I
08
b1 "
b1 0
b1 >
b1 ?
b0 P
b0 Q
b0 G
b0 H
b0 6
b0 7
b1 /
b1 <
1;
0M
0D
03
b1 =
b1 A
b11 )
b1 %
b1 +
0&
1'
#80
0'
#90
0#
0!
01
0B
b1 .
b1 N
b1 -
b1 E
b1 ,
b1 4
b1 O
b1 S
b1 F
b1 J
b1 5
b1 9
0K
0@
1R
1I
18
b1111 "
b1111 0
b0 >
b0 ?
b1 P
b1 Q
b1 G
b1 H
b1 6
b1 7
b1 /
b1 <
0;
1M
1D
13
b1 =
b1 A
b100 )
1&
1'
#100
0'
#110
b1 .
b1 N
b0 -
b0 E
b0 ,
b0 4
b1 O
b1 S
b0 F
b0 J
b0 5
b0 9
0@
1R
0I
08
b10 "
b10 0
b0 >
b0 ?
b1 P
b1 Q
b0 G
b0 H
b0 6
b0 7
b0 /
b0 <
0;
1M
0D
03
b0 =
b0 A
b101 )
b10 %
b10 +
0&
1'
#120
0'
#130
1K
b1 .
b1 N
b1 -
b1 E
b1 ,
b1 4
b1 O
b1 S
b1 F
b1 J
b1 5
b1 9
1@
0R
1I
18
b1110 "
b1110 0
b1 >
b1 ?
b0 P
b0 Q
b1 G
b1 H
b1 6
b1 7
b10 /
b10 <
1;
0M
1D
13
b10 =
b10 A
b110 )
1&
1'
#140
0'
#150
b0 -
b0 E
b0 ,
b0 4
b0 F
b0 J
b0 5
b0 9
0K
1@
1R
0I
08
b11 "
b11 0
b1 >
b1 ?
b1 P
b1 Q
b0 G
b0 H
b0 6
b0 7
b1 /
b1 <
1;
1M
0D
03
b1 =
b1 A
b111 )
b11 %
b11 +
0&
1'
#160
0'
#170
b0 .
b0 N
b0 O
b0 S
b1 -
b1 E
b1 ,
b1 4
b1 F
b1 J
b1 5
b1 9
0K
0@
0R
1I
18
b1101 "
b1101 0
b0 >
b0 ?
b0 P
b0 Q
b1 G
b1 H
b1 6
b1 7
b1 /
b1 <
0;
0M
1D
13
b1 =
b1 A
b1000 )
1&
1'
#180
0'
#190
b0 .
b0 N
b1 -
b1 E
b0 ,
b0 4
b0 O
b0 S
b1 F
b1 J
b0 5
b0 9
0@
0R
1I
08
b100 "
b100 0
b0 >
b0 ?
b0 P
b0 Q
b1 G
b1 H
b0 6
b0 7
b0 /
b0 <
0;
0M
1D
03
b0 =
b0 A
b1001 )
b100 %
b100 +
0&
1'
#200
0'
#210
1B
1K
b10 .
b10 N
b1 -
b1 E
b1 ,
b1 4
b10 O
b10 S
b1 F
b1 J
b1 5
b1 9
1@
1R
0I
18
b1100 "
b1100 0
b1 >
b1 ?
b1 P
b1 Q
b0 G
b0 H
b1 6
b1 7
b10 /
b10 <
1;
1M
0D
13
b10 =
b10 A
b1010 )
1&
1'
#220
0'
#230
0!
0B
01
b0 .
b0 N
b1 -
b1 E
b0 ,
b0 4
b0 O
b0 S
b1 F
b1 J
b0 5
b0 9
0K
1@
0R
1I
08
b101 "
b101 0
b1 >
b1 ?
b0 P
b0 Q
b1 G
b1 H
b0 6
b0 7
b1 /
b1 <
1;
0M
1D
03
b1 =
b1 A
b1011 )
b101 %
b101 +
0&
1'
#240
0'
#250
0B
b1 .
b1 N
b0 -
b0 E
b1 ,
b1 4
b1 O
b1 S
b0 F
b0 J
b1 5
b1 9
0K
0@
1R
0I
18
b1011 "
b1011 0
b0 >
b0 ?
b1 P
b1 Q
b0 G
b0 H
b1 6
b1 7
b1 /
b1 <
0;
1M
0D
13
b1 =
b1 A
b1100 )
1&
1'
#260
0'
#270
b1 .
b1 N
b1 -
b1 E
b0 ,
b0 4
b1 O
b1 S
b1 F
b1 J
b0 5
b0 9
0@
1R
1I
08
b110 "
b110 0
b0 >
b0 ?
b1 P
b1 Q
b1 G
b1 H
b0 6
b0 7
b0 /
b0 <
0;
1M
1D
03
b0 =
b0 A
b1101 )
b110 %
b110 +
0&
1'
#280
0'
#290
1K
b1 .
b1 N
b0 -
b0 E
b1 ,
b1 4
b1 O
b1 S
b0 F
b0 J
b1 5
b1 9
1@
0R
0I
18
b1010 "
b1010 0
b1 >
b1 ?
b0 P
b0 Q
b0 G
b0 H
b1 6
b1 7
b10 /
b10 <
1;
0M
0D
13
b10 =
b10 A
b1110 )
1&
1'
#300
0'
#310
b1 -
b1 E
b0 ,
b0 4
b1 F
b1 J
b0 5
b0 9
0K
1@
1R
1I
08
b111 "
b111 0
b1 >
b1 ?
b1 P
b1 Q
b1 G
b1 H
b0 6
b0 7
b1 /
b1 <
1;
1M
1D
03
b1 =
b1 A
b1111 )
b111 %
b111 +
0&
1'
#320
0'
#330
b0 .
b0 N
b0 O
b0 S
b0 -
b0 E
b1 ,
b1 4
b0 F
b0 J
b1 5
b1 9
0K
0@
0R
0I
18
b1001 "
b1001 0
b0 >
b0 ?
b0 P
b0 Q
b0 G
b0 H
b1 6
b1 7
b1 /
b1 <
0;
0M
0D
13
b1 =
b1 A
b10000 )
1&
1'
#340
0'
#350
b0 .
b0 N
b0 -
b0 E
b1 ,
b1 4
b0 O
b0 S
b0 F
b0 J
b1 5
b1 9
0@
0R
0I
18
b1000 "
b1000 0
b0 >
b0 ?
b0 P
b0 Q
b0 G
b0 H
b1 6
b1 7
b0 /
b0 <
0;
0M
0D
13
b0 =
b0 A
b10001 )
b1000 %
b1000 +
0&
1'
#360
0'
#370
1!
11
1B
1K
b10 .
b10 N
b10 -
b10 E
b1 ,
b1 4
b10 O
b10 S
b10 F
b10 J
b1 5
b1 9
1@
1R
1I
08
b1000 "
b1000 0
b1 >
b1 ?
b1 P
b1 Q
b1 G
b1 H
b0 6
b0 7
b10 /
b10 <
1;
1M
1D
03
b10 =
b10 A
b10010 )
1&
1'
#380
0'
#390
0!
0B
01
0#
b0 .
b0 N
b0 -
b0 E
b1 ,
b1 4
b0 O
b0 S
b0 F
b0 J
b1 5
b1 9
0K
1@
0R
0I
18
b1001 "
b1001 0
b1 >
b1 ?
b0 P
b0 Q
b0 G
b0 H
b1 6
b1 7
b1 /
b1 <
1;
0M
0D
13
b1 =
b1 A
b10011 )
b1001 %
b1001 +
0&
1'
#400
0'
#410
0!
01
0B
b1 .
b1 N
b1 -
b1 E
b0 ,
b0 4
b1 O
b1 S
b1 F
b1 J
b0 5
b0 9
0K
0@
1R
1I
08
b111 "
b111 0
b0 >
b0 ?
b1 P
b1 Q
b1 G
b1 H
b0 6
b0 7
b1 /
b1 <
0;
1M
1D
03
b1 =
b1 A
b10100 )
1&
1'
#420
0'
#430
b1 .
b1 N
b0 -
b0 E
b1 ,
b1 4
b1 O
b1 S
b0 F
b0 J
b1 5
b1 9
0@
1R
0I
18
b1010 "
b1010 0
b0 >
b0 ?
b1 P
b1 Q
b0 G
b0 H
b1 6
b1 7
b0 /
b0 <
0;
1M
0D
13
b0 =
b0 A
b10101 )
b1010 %
b1010 +
0&
1'
#440
0'
#450
1K
b1 .
b1 N
b1 -
b1 E
b0 ,
b0 4
b1 O
b1 S
b1 F
b1 J
b0 5
b0 9
1@
0R
1I
08
b110 "
b110 0
b1 >
b1 ?
b0 P
b0 Q
b1 G
b1 H
b0 6
b0 7
b10 /
b10 <
1;
0M
1D
03
b10 =
b10 A
b10110 )
1&
1'
#460
0'
#470
b0 -
b0 E
b1 ,
b1 4
b0 F
b0 J
b1 5
b1 9
0K
1@
1R
0I
18
b1011 "
b1011 0
b1 >
b1 ?
b1 P
b1 Q
b0 G
b0 H
b1 6
b1 7
b1 /
b1 <
1;
1M
0D
13
b1 =
b1 A
b10111 )
b1011 %
b1011 +
0&
1'
#480
0'
#490
b0 .
b0 N
b0 O
b0 S
b1 -
b1 E
b0 ,
b0 4
b1 F
b1 J
b0 5
b0 9
0K
0@
0R
1I
08
b101 "
b101 0
b0 >
b0 ?
b0 P
b0 Q
b1 G
b1 H
b0 6
b0 7
b1 /
b1 <
0;
0M
1D
03
b1 =
b1 A
b11000 )
1&
1'
#500
0'
#510
b0 .
b0 N
b1 -
b1 E
b1 ,
b1 4
b0 O
b0 S
b1 F
b1 J
b1 5
b1 9
0@
0R
1I
18
b1100 "
b1100 0
b0 >
b0 ?
b0 P
b0 Q
b1 G
b1 H
b1 6
b1 7
b0 /
b0 <
0;
0M
1D
13
b0 =
b0 A
b11001 )
b1100 %
b1100 +
0&
1'
#520
0'
#530
1B
1K
b10 .
b10 N
b1 -
b1 E
b0 ,
b0 4
b10 O
b10 S
b1 F
b1 J
b0 5
b0 9
1@
1R
0I
08
b100 "
b100 0
b1 >
b1 ?
b1 P
b1 Q
b0 G
b0 H
b0 6
b0 7
b10 /
b10 <
1;
1M
0D
03
b10 =
b10 A
b11010 )
1&
1'
#540
0'
#550
0#
0!
0B
01
b0 .
b0 N
b1 -
b1 E
b1 ,
b1 4
b0 O
b0 S
b1 F
b1 J
b1 5
b1 9
0K
1@
0R
1I
18
b1101 "
b1101 0
b1 >
b1 ?
b0 P
b0 Q
b1 G
b1 H
b1 6
b1 7
b1 /
b1 <
1;
0M
1D
13
b1 =
b1 A
b11011 )
b1101 %
b1101 +
0&
1'
#560
0'
#570
0B
b1 .
b1 N
b0 -
b0 E
b0 ,
b0 4
b1 O
b1 S
b0 F
b0 J
b0 5
b0 9
0K
0@
1R
0I
08
b11 "
b11 0
b0 >
b0 ?
b1 P
b1 Q
b0 G
b0 H
b0 6
b0 7
b1 /
b1 <
0;
1M
0D
03
b1 =
b1 A
b11100 )
1&
1'
#580
0'
#590
b1 .
b1 N
b1 -
b1 E
b1 ,
b1 4
b1 O
b1 S
b1 F
b1 J
b1 5
b1 9
0@
1R
1I
18
b1110 "
b1110 0
b0 >
b0 ?
b1 P
b1 Q
b1 G
b1 H
b1 6
b1 7
b0 /
b0 <
0;
1M
1D
13
b0 =
b0 A
b11101 )
b1110 %
b1110 +
0&
1'
#600
0'
#610
1K
b1 .
b1 N
b0 -
b0 E
b0 ,
b0 4
b1 O
b1 S
b0 F
b0 J
b0 5
b0 9
1@
0R
0I
08
b10 "
b10 0
b1 >
b1 ?
b0 P
b0 Q
b0 G
b0 H
b0 6
b0 7
b10 /
b10 <
1;
0M
0D
03
b10 =
b10 A
b11110 )
1&
1'
#620
0'
#630
b1 -
b1 E
b1 ,
b1 4
b1 F
b1 J
b1 5
b1 9
0K
1@
1R
1I
18
b1111 "
b1111 0
b1 >
b1 ?
b1 P
b1 Q
b1 G
b1 H
b1 6
b1 7
b1 /
b1 <
1;
1M
1D
13
b1 =
b1 A
b11111 )
b1111 %
b1111 +
0&
1'
#640
0'
#650
b0 .
b0 N
b0 O
b0 S
b0 -
b0 E
b0 ,
b0 4
b0 F
b0 J
b0 5
b0 9
0K
0@
0R
0I
08
b1 "
b1 0
b0 >
b0 ?
b0 P
b0 Q
b0 G
b0 H
b0 6
b0 7
b1 /
b1 <
0;
0M
0D
03
b1 =
b1 A
b100000 )
1&
1'
#660
0'
#670
0K
b0 .
b0 N
b0 -
b0 E
b0 ,
b0 4
1@
b0 O
b0 S
b0 F
b0 J
b0 5
b0 9
0R
0I
08
b1 "
b1 0
b1 >
b1 ?
b0 P
b0 Q
b0 G
b0 H
b0 6
b0 7
b1 /
b1 <
1:
0;
0M
0D
03
b1 =
b1 A
b100001 )
b1 $
b1 *
b0 %
b0 +
0&
1'
#680
0'
#690
1#
0!
11
1B
b10 .
b10 N
b10 -
b10 E
b10 ,
b10 4
b10 O
b10 S
b10 F
b10 J
b10 5
b10 9
1K
0@
1R
1I
18
b1 "
b1 0
b10 >
b10 ?
b1 P
b1 Q
b1 G
b1 H
b1 6
b1 7
b11 /
b11 <
1;
1M
1D
13
b1 =
b1 A
b100010 )
1&
1'
#700
0'
#710
0B
01
0#
1K
b1 .
b1 N
b0 -
b0 E
b0 ,
b0 4
b1 O
b1 S
b0 F
b0 J
b0 5
b0 9
0@
0R
0I
08
b10 "
b10 0
b10 >
b10 ?
b0 P
b0 Q
b0 G
b0 H
b0 6
b0 7
b10 /
b10 <
1;
0M
0D
03
b0 =
b0 A
b100011 )
b1 %
b1 +
0&
1'
#720
0'
#730
1#
0!
11
1B
1K
b10 .
b10 N
b10 -
b10 E
b10 ,
b10 4
b10 O
b10 S
b10 F
b10 J
b10 5
b10 9
1@
1R
1I
18
b0 "
b0 0
b1 >
b1 ?
b1 P
b1 Q
b1 G
b1 H
b1 6
b1 7
b10 /
b10 <
0;
1M
1D
13
b10 =
b10 A
b100100 )
1&
1'
#740
0'
#750
0B
01
0#
b1 .
b1 N
b0 -
b0 E
b0 ,
b0 4
b1 O
b1 S
b0 F
b0 J
b0 5
b0 9
0K
1@
1R
0I
08
b11 "
b11 0
b1 >
b1 ?
b1 P
b1 Q
b0 G
b0 H
b0 6
b0 7
b1 /
b1 <
0;
1M
0D
03
b1 =
b1 A
b100101 )
b10 %
b10 +
0&
1'
#760
0'
#770
b1 -
b1 E
b1 ,
b1 4
b1 F
b1 J
b1 5
b1 9
1K
0@
0R
1I
18
b1111 "
b1111 0
b10 >
b10 ?
b0 P
b0 Q
b1 G
b1 H
b1 6
b1 7
b11 /
b11 <
1;
0M
1D
13
b1 =
b1 A
b100110 )
1&
1'
#780
0'
#790
1B
1K
b10 .
b10 N
b1 -
b1 E
b0 ,
b0 4
b10 O
b10 S
b1 F
b1 J
b0 5
b0 9
0@
1R
0I
08
b100 "
b100 0
b10 >
b10 ?
b1 P
b1 Q
b0 G
b0 H
b0 6
b0 7
b10 /
b10 <
1;
1M
0D
03
b0 =
b0 A
b100111 )
b11 %
b11 +
0&
1'
#800
0'
#810
0#
0!
0B
01
1K
b1 .
b1 N
b1 -
b1 E
b1 ,
b1 4
b1 O
b1 S
b1 F
b1 J
b1 5
b1 9
1@
0R
1I
18
b1110 "
b1110 0
b1 >
b1 ?
b0 P
b0 Q
b1 G
b1 H
b1 6
b1 7
b10 /
b10 <
0;
0M
1D
13
b10 =
b10 A
b101000 )
1&
1'
#820
0'
#830
b0 .
b0 N
b0 O
b0 S
b1 -
b1 E
b0 ,
b0 4
b1 F
b1 J
b0 5
b0 9
0K
1@
0R
1I
08
b101 "
b101 0
b1 >
b1 ?
b0 P
b0 Q
b1 G
b1 H
b0 6
b0 7
b1 /
b1 <
0;
0M
1D
03
b1 =
b1 A
b101001 )
b100 %
b100 +
0&
1'
#840
0'
#850
1B
b10 .
b10 N
b1 -
b1 E
b1 ,
b1 4
b10 O
b10 S
b1 F
b1 J
b1 5
b1 9
1K
0@
1R
0I
18
b1101 "
b1101 0
b10 >
b10 ?
b1 P
b1 Q
b0 G
b0 H
b1 6
b1 7
b11 /
b11 <
1;
1M
0D
13
b1 =
b1 A
b101010 )
1&
1'
#860
0'
#870
0!
0B
01
1K
b1 .
b1 N
b1 -
b1 E
b0 ,
b0 4
b1 O
b1 S
b1 F
b1 J
b0 5
b0 9
0@
0R
1I
08
b110 "
b110 0
b10 >
b10 ?
b0 P
b0 Q
b1 G
b1 H
b0 6
b0 7
b10 /
b10 <
1;
0M
1D
03
b0 =
b0 A
b101011 )
b101 %
b101 +
0&
1'
#880
0'
#890
1B
1K
b10 .
b10 N
b1 -
b1 E
b1 ,
b1 4
b10 O
b10 S
b1 F
b1 J
b1 5
b1 9
1@
1R
0I
18
b1100 "
b1100 0
b1 >
b1 ?
b1 P
b1 Q
b0 G
b0 H
b1 6
b1 7
b10 /
b10 <
0;
1M
0D
13
b10 =
b10 A
b101100 )
1&
1'
#900
0'
#910
0!
0B
01
b1 .
b1 N
b1 -
b1 E
b0 ,
b0 4
b1 O
b1 S
b1 F
b1 J
b0 5
b0 9
0K
1@
1R
1I
08
b111 "
b111 0
b1 >
b1 ?
b1 P
b1 Q
b1 G
b1 H
b0 6
b0 7
b1 /
b1 <
0;
1M
1D
03
b1 =
b1 A
b101101 )
b110 %
b110 +
0&
1'
#920
0'
#930
b0 -
b0 E
b1 ,
b1 4
b0 F
b0 J
b1 5
b1 9
1K
0@
0R
0I
18
b1011 "
b1011 0
b10 >
b10 ?
b0 P
b0 Q
b0 G
b0 H
b1 6
b1 7
b11 /
b11 <
1;
0M
0D
13
b1 =
b1 A
b101110 )
1&
1'
#940
0'
#950
1!
11
1B
1K
b10 .
b10 N
b10 -
b10 E
b1 ,
b1 4
b10 O
b10 S
b10 F
b10 J
b1 5
b1 9
0@
1R
1I
08
b1000 "
b1000 0
b10 >
b10 ?
b1 P
b1 Q
b1 G
b1 H
b0 6
b0 7
b10 /
b10 <
1;
1M
1D
03
b0 =
b0 A
b101111 )
b111 %
b111 +
0&
1'
#960
0'
#970
0!
0B
01
0#
1K
b1 .
b1 N
b0 -
b0 E
b1 ,
b1 4
b1 O
b1 S
b0 F
b0 J
b1 5
b1 9
1@
0R
0I
18
b1010 "
b1010 0
b1 >
b1 ?
b0 P
b0 Q
b0 G
b0 H
b1 6
b1 7
b10 /
b10 <
0;
0M
0D
13
b10 =
b10 A
b110000 )
1&
1'
#980
0'
#990
b0 .
b0 N
b0 O
b0 S
b0 -
b0 E
b1 ,
b1 4
b0 F
b0 J
b1 5
b1 9
0K
1@
0R
0I
18
b1001 "
b1001 0
b1 >
b1 ?
b0 P
b0 Q
b0 G
b0 H
b1 6
b1 7
b1 /
b1 <
0;
0M
0D
13
b1 =
b1 A
b110001 )
b1000 %
b1000 +
0&
1'
#1000
0'
#1010
1!
11
1B
b10 .
b10 N
b10 -
b10 E
b1 ,
b1 4
b10 O
b10 S
b10 F
b10 J
b1 5
b1 9
1K
0@
1R
1I
08
b1001 "
b1001 0
b10 >
b10 ?
b1 P
b1 Q
b1 G
b1 H
b0 6
b0 7
b11 /
b11 <
1;
1M
1D
03
b1 =
b1 A
b110010 )
1&
1'
#1020
0'
#1030
0!
0B
01
0#
1K
b1 .
b1 N
b0 -
b0 E
b1 ,
b1 4
b1 O
b1 S
b0 F
b0 J
b1 5
b1 9
0@
0R
0I
18
b1010 "
b1010 0
b10 >
b10 ?
b0 P
b0 Q
b0 G
b0 H
b1 6
b1 7
b10 /
b10 <
1;
0M
0D
13
b0 =
b0 A
b110011 )
b1001 %
b1001 +
0&
1'
#1040
0'
#1050
1!
11
1B
1K
b10 .
b10 N
b10 -
b10 E
b1 ,
b1 4
b10 O
b10 S
b10 F
b10 J
b1 5
b1 9
1@
1R
1I
08
b1000 "
b1000 0
b1 >
b1 ?
b1 P
b1 Q
b1 G
b1 H
b0 6
b0 7
b10 /
b10 <
0;
1M
1D
03
b10 =
b10 A
b110100 )
1&
1'
#1060
0'
#1070
0!
0B
01
0#
b1 .
b1 N
b0 -
b0 E
b1 ,
b1 4
b1 O
b1 S
b0 F
b0 J
b1 5
b1 9
0K
1@
1R
0I
18
b1011 "
b1011 0
b1 >
b1 ?
b1 P
b1 Q
b0 G
b0 H
b1 6
b1 7
b1 /
b1 <
0;
1M
0D
13
b1 =
b1 A
b110101 )
b1010 %
b1010 +
0&
1'
#1080
0'
#1090
b1 -
b1 E
b0 ,
b0 4
b1 F
b1 J
b0 5
b0 9
1K
0@
0R
1I
08
b111 "
b111 0
b10 >
b10 ?
b0 P
b0 Q
b1 G
b1 H
b0 6
b0 7
b11 /
b11 <
1;
0M
1D
03
b1 =
b1 A
b110110 )
1&
1'
#1100
0'
#1110
1B
1K
b10 .
b10 N
b1 -
b1 E
b1 ,
b1 4
b10 O
b10 S
b1 F
b1 J
b1 5
b1 9
0@
1R
0I
18
b1100 "
b1100 0
b10 >
b10 ?
b1 P
b1 Q
b0 G
b0 H
b1 6
b1 7
b10 /
b10 <
1;
1M
0D
13
b0 =
b0 A
b110111 )
b1011 %
b1011 +
0&
1'
#1120
0'
#1130
0!
0B
01
1K
b1 .
b1 N
b1 -
b1 E
b0 ,
b0 4
b1 O
b1 S
b1 F
b1 J
b0 5
b0 9
1@
0R
1I
08
b110 "
b110 0
b1 >
b1 ?
b0 P
b0 Q
b1 G
b1 H
b0 6
b0 7
b10 /
b10 <
0;
0M
1D
03
b10 =
b10 A
b111000 )
1&
1'
#1140
0'
#1150
b0 .
b0 N
b0 O
b0 S
b1 -
b1 E
b1 ,
b1 4
b1 F
b1 J
b1 5
b1 9
0K
1@
0R
1I
18
b1101 "
b1101 0
b1 >
b1 ?
b0 P
b0 Q
b1 G
b1 H
b1 6
b1 7
b1 /
b1 <
0;
0M
1D
13
b1 =
b1 A
b111001 )
b1100 %
b1100 +
0&
1'
#1160
0'
#1170
1B
b10 .
b10 N
b1 -
b1 E
b0 ,
b0 4
b10 O
b10 S
b1 F
b1 J
b0 5
b0 9
1K
0@
1R
0I
08
b101 "
b101 0
b10 >
b10 ?
b1 P
b1 Q
b0 G
b0 H
b0 6
b0 7
b11 /
b11 <
1;
1M
0D
03
b1 =
b1 A
b111010 )
1&
1'
#1180
0'
#1190
0#
0!
0B
01
1K
b1 .
b1 N
b1 -
b1 E
b1 ,
b1 4
b1 O
b1 S
b1 F
b1 J
b1 5
b1 9
0@
0R
1I
18
b1110 "
b1110 0
b10 >
b10 ?
b0 P
b0 Q
b1 G
b1 H
b1 6
b1 7
b10 /
b10 <
1;
0M
1D
13
b0 =
b0 A
b111011 )
b1101 %
b1101 +
0&
1'
#1200
0'
#1210
1B
1K
b10 .
b10 N
b1 -
b1 E
b0 ,
b0 4
b10 O
b10 S
b1 F
b1 J
b0 5
b0 9
1@
1R
0I
08
b100 "
b100 0
b1 >
b1 ?
b1 P
b1 Q
b0 G
b0 H
b0 6
b0 7
b10 /
b10 <
0;
1M
0D
03
b10 =
b10 A
b111100 )
1&
1'
#1220
0'
#1230
0#
0!
0B
01
b1 .
b1 N
b1 -
b1 E
b1 ,
b1 4
b1 O
b1 S
b1 F
b1 J
b1 5
b1 9
0K
1@
1R
1I
18
b1111 "
b1111 0
b1 >
b1 ?
b1 P
b1 Q
b1 G
b1 H
b1 6
b1 7
b1 /
b1 <
0;
1M
1D
13
b1 =
b1 A
b111101 )
b1110 %
b1110 +
0&
1'
#1240
0'
#1250
b0 -
b0 E
b0 ,
b0 4
b0 F
b0 J
b0 5
b0 9
1K
0@
0R
0I
08
b11 "
b11 0
b10 >
b10 ?
b0 P
b0 Q
b0 G
b0 H
b0 6
b0 7
b11 /
b11 <
1;
0M
0D
03
b1 =
b1 A
b111110 )
1&
1'
#1260
0'
#1270
1#
0!
11
1B
1K
b10 .
b10 N
b10 -
b10 E
b10 ,
b10 4
b10 O
b10 S
b10 F
b10 J
b10 5
b10 9
0@
1R
1I
18
b0 "
b0 0
b10 >
b10 ?
b1 P
b1 Q
b1 G
b1 H
b1 6
b1 7
b10 /
b10 <
1;
1M
1D
13
b0 =
b0 A
b111111 )
b1111 %
b1111 +
0&
1'
#1280
0'
#1290
0B
01
0#
1K
b1 .
b1 N
b0 -
b0 E
b0 ,
b0 4
b1 O
b1 S
b0 F
b0 J
b0 5
b0 9
1@
0R
0I
08
b10 "
b10 0
b1 >
b1 ?
b0 P
b0 Q
b0 G
b0 H
b0 6
b0 7
b10 /
b10 <
0;
0M
0D
03
b10 =
b10 A
b1000000 )
1&
1'
#1300
0'
#1310
0B
b0 -
b0 E
b0 ,
b0 4
0@
1R
b1 .
b1 N
b0 F
b0 J
b0 5
b0 9
0K
b0 >
b0 ?
0I
08
b10 "
b10 0
b1 P
b1 Q
b0 G
b0 H
b0 6
b0 7
b0 /
b0 <
0:
1L
0;
0M
0D
03
b0 =
b0 A
b1000001 )
b10 $
b10 *
b0 %
b0 +
0&
1'
#1320
0'
